Workbook

Sheet ReadMe
A1: Final Model
A4: Project | B4: 50 MW / 500 MWh behind-the-meter battery supplying a new 50 MW co-location load's Bring Your Own New Capacity (BYONC) under PJM IRAS (Dominion zone, Loudoun County), in service 1 June 2029.
A5: Basis | B5: Nominal US$ million, annual, end of period. Model years are PJM delivery years (1 June – 31 May): Year 0 = 2028/29 (construction), Years 1–15 = 2029/30 – 2043/44 (operation from 1 June 2029). Valued at the end of Year 0. Taxes use the same annual periods (simplification).
A6: Signs | B6: Inflows positive (+), outflows negative (-). DSCR = CFADS ÷ |debt service|.
A7: Colours | B7: Orange fill = input; green fill = link to Inputs; yellow fill = key result; no fill = formula.
A8: Sheets | B8: Inputs → Events (PJM demand-response days, Dominion zone) → Technical → Costs → CashFlow → Results → Sensitivity → Customer.
A9: Goal Seek | B9: Goal Seek finds the fee that gives equity exactly a 12% return. Route: Data → What-If Analysis → Goal Seek; set Results!B23 to 0 by changing Inputs!C30. Re-run it after changing any input.
A10: Sensitivity | B10: 1. Fee by case: the minimum fee in 13 cases, e.g. low/high cost, capacity price, O&M, 5 h or 15 h, tax credit, interest rate, no recharge. 2. Case results: days covered, CAPEX and PJM charges in each case. 3. Cost limit: the highest CAPEX that still works if the customer will pay only $35, $30, $25 or the RBP cost.
A11: Traceability | B11: Base-case results: Results sheet. Sensitivity cases and thresholds: Sensitivity sheet. Customer-side comparisons (RBP, gas, rent): Customer sheet.

Sheet Inputs
A1: INPUTS AND SOURCES
B4: Parameter | C4: Value | D4: Unit | E4: Evidence | F4: Source
A5: A. Timing and model basis
B6: Construction year (Year 0 = Jun 2028 – May 2029) | C6: 2028 | D6: year | E6: Own design choice | F6: Report Section 10 schedule.
B7: Contract term = operating life | C7: 15 | D7: years | E7: Own design choice | F7: NREL (2025) p.12.
B8: Inflation / cost escalation | C8: 0.025 | D8: %/year | E8: Sourced | F8: Lazard LCOE+ (Jul 2026).
B9: Dollar year of NREL cost inputs | C9: 2024 | D9: year | E9: Sourced | F9: NREL (2025).
B10: Dollar year of charging price | C10: 2025 | D10: year | E10: Sourced | F10: PJM Data Miner 2.
A11: B. Customer load, PJM capacity requirement and battery performance
B12: New Large Load of the customer | C12: 50 | D12: MW | E12: Sourced | F12: PJM CIFP proposal (27 Jul 2026).
B13: Forecast Pool Requirement, 2029/30 | C13: 0.9232 | D13: ratio | E13: Sourced | F13: PJM 2029/30 BRA planning parameters (3 Sep 2026).
B14: Demand Resource accreditation, first delivery year 2029/30 | C14: 0.9 | D14: % | E14: Sourced; applied beyond its basis | F14: PJM ELCC class ratings, 2029/30 BRA.
B15: 10-hour storage accreditation, 2029/30 (rating comparison) | C15: 0.76 | D15: % | E15: Sourced | F15: PJM ELCC class ratings, 2029/30 BRA.
B16: Data center PUE (industry weighted average) | C16: 1.54 | D16: ratio | E16: Sourced; applied beyond its basis | F16: Uptime Institute survey (2025).
B17: Round-trip efficiency (AC, incl. auxiliary cooling) | C17: 0.85 | D17: % | E17: Sourced | F17: NREL (2025) p.12.
A18: C. Capital cost and tax credit
B19: Energy-related installed cost (2024$) | C19: 241 | D19: $/kWh | E19: Sourced | F19: NREL (2025) p.6.
B20: Power-related installed cost (2024$) | C20: 372 | D20: $/kW | E20: Sourced | F20: NREL (2025) p.6.
B21: Investment tax credit rate | C21: 0.3 | D21: % | E21: Sourced | F21: IRS §48E; Notice 2026-15.
B22: Tax credit value when sold | C22: 0.9 | D22: $ per $1 credit | E22: Sourced | F22: Norton Rose Fulbright (Jan 2026).
B23: Depreciable basis reduction per $1 of credit | C23: 0.5 | D23: $ per $1 | E23: Sourced | F23: 26 U.S.C. §50(c)(3).
A24: D. Operating cost
B25: Fixed O&M incl. augmentation | C25: 0.04 | D25: % of NREL capital cost per yr | E25: Sourced; applied beyond its basis | F25: NREL (2025) p.11.
B26: Insurance | C26: 0.004 | D26: % of CAPEX per year | E26: Sourced; applied beyond its basis | F26: PNNL (2024).
B27: Property tax | C27: 0.0084 | D27: % of CAPEX per year | E27: Sourced; applied beyond its basis | F27: PNNL (2024).
B28: Charging energy price (2025$) | C28: 47.53 | D28: $/MWh | E28: Sourced; held constant by judgment | F28: PJM Data Miner 2 (DOM, 2025).
A29: E. Revenue
B30: Availability fee per kW of load (Goal Seek) | C30: 27.653459 | D30: $/kW-month | E30: Model output | F30: Goal Seek output.
B31: Fee escalation | C31: 0 | D31: %/year | E31: Own design choice | F31: Contract design.
B32: Capacity price proxy (2029/30 RPM price cap) | C32: 337.83 | D32: $/MW-day UCAP | E32: Sourced; held constant by judgment | F32: PJM 2029/30 planning parameters (ER26-1556).
B33: Capacity price escalation | C33: 0 | D33: %/year nominal | E33: Sourced; held constant by judgment | F33: Held flat (judgment).
A34: F. Customer value benchmark
B35: Northern Virginia colocation asking rate (low end) | C35: 160 | D35: $/kW-month | E35: Sourced; point chosen from a range | F35: CBRE H1 2026.
A36: G. Tax
B37: Federal corporate income tax | C37: 0.21 | D37: % | E37: Sourced | F37: 26 U.S.C. §11(b).
B38: Virginia corporate income tax | C38: 0.06 | D38: % | E38: Sourced | F38: Va. Code Ann. §58.1-400.
B39: Loss carryforward limit | C39: 0.8 | D39: % of taxable income | E39: Sourced | F39: 26 U.S.C. §172(a).
B40: MACRS 5-year rate, tax year 1 | C40: 0.2 | D40: % of basis | E40: Sourced | F40: IRS Publication 946, Table A-1.
B41: MACRS 5-year rate, tax year 2 | C41: 0.32 | D41: % of basis | E41: Sourced
B42: MACRS 5-year rate, tax year 3 | C42: 0.192 | D42: % of basis | E42: Sourced
B43: MACRS 5-year rate, tax year 4 | C43: 0.1152 | D43: % of basis | E43: Sourced
B44: MACRS 5-year rate, tax year 5 | C44: 0.1152 | D44: % of basis | E44: Sourced
B45: MACRS 5-year rate, tax year 6 | C45: 0.0576 | D45: % of basis | E45: Sourced
A46: H. Financing
B47: Base rate: 10-year U.S. Treasury yield (3 Sep 2026) | C47: 0.0477 | D47: % | E47: Sourced | F47: Federal Reserve H.15 (4 Sep 2026).
B48: Term-debt margin (middle of fairway) | C48: 0.0175 | D48: % | E48: Sourced; point chosen from a range | F48: Norton Rose Fulbright (Jan 2026).
B49: Battery storage premium | C49: 0.0025 | D49: % | E49: Sourced | F49: Norton Rose Fulbright (Jan 2025).
B50: Uncontracted revenue share, first premium step | C50: 0.1 | D50: % of revenue | E50: Sourced | F50: Norton Rose Fulbright (Jan 2026).
B51: Premium at the first step | C51: 0.0025 | D51: % | E51: Sourced | F51: Same source.
B52: Uncontracted revenue share, second premium step | C52: 0.3 | D52: % of revenue | E52: Sourced | F52: Norton Rose Fulbright (Jan 2026).
B53: Additional premium at the second step | C53: 0.0025 | D53: % | E53: Sourced | F53: Same source.
B54: Debt tenor | C54: 15 | D54: years | E54: Sourced | F54: Lazard LCOE+ (Jul 2026).
B55: Minimum DSCR, contracted storage revenue | C55: 1.2 | D55: x | E55: Sourced; point chosen from a range | F55: Norton Rose Fulbright (Jan 2026).
B56: Minimum DSCR, merchant storage revenue | C56: 2 | D56: x | E56: Sourced | F56: Norton Rose Fulbright (Jan 2026).
B57: Target equity IRR (cost of equity) | C57: 0.12 | D57: % | E57: Sourced | F57: Lazard LCOE+ (Jul 2026).
A58: I. Design duration, dispatch record and PJM performance charges
B59: Design duration (battery energy ÷ power) | C59: 10 | D59: h | E59: Own design choice | F59: Events sheet.
B60: Length of the event record | C60: 9.72 | D60: years | E60: Sourced | F60: PJM Emergency Procedures postings.
B61: Battery forced-outage rate in event hours | C61: 0.0894 | D61: % | E61: Sourced; applied beyond its basis | F61: CPUC UCAP workshop (3 Nov 2025), slide 47.
B62: Net CONE, RTO, 2029/30 (installed capacity) | C62: 261.79 | D62: $/MW-day | E62: Sourced | F62: PJM 2029/30 planning parameters.
B63: Charge on non-PAI shortfalls, share of full rate | C63: 0.5 | D63: % | E63: Sourced | F63: FERC ER26-2319; PJM Manual 18.
A64: J. PJM Demand Resource accreditation by delivery year (drives capacity revenue)
B65: Demand Resource ELCC class rating, 2029/30 | C65: =C14 -> 0.9 | D65: % | E65: Sourced | F65: Row 14.
B66: Demand Resource ELCC class rating, 2030/31 | C66: 0.84 | D66: % | E66: Indicative (PJM preliminary, non-binding) | F66: PJM preliminary ELCC ratings (31 Aug 2026).
B67: Demand Resource ELCC class rating, 2031/32 | C67: 0.82 | D67: % | E67: Indicative (PJM preliminary, non-binding) | F67: PJM preliminary ELCC ratings (31 Aug 2026).
B68: Demand Resource ELCC class rating, 2032/33 | C68: 0.82 | D68: % | E68: Indicative (PJM preliminary, non-binding) | F68: PJM preliminary ELCC ratings (31 Aug 2026).
B69: Demand Resource ELCC class rating, 2033/34 | C69: 0.8 | D69: % | E69: Indicative (PJM preliminary, non-binding) | F69: PJM preliminary ELCC ratings (31 Aug 2026).
B70: Demand Resource ELCC class rating, 2034/35 | C70: 0.78 | D70: % | E70: Indicative (PJM preliminary, non-binding) | F70: PJM preliminary ELCC ratings (31 Aug 2026).
B71: Demand Resource ELCC class rating, 2035/36 | C71: 0.76 | D71: % | E71: Indicative (PJM preliminary, non-binding) | F71: PJM preliminary ELCC ratings (31 Aug 2026).
B72: Demand Resource ELCC class rating, 2036/37 | C72: 0.75 | D72: % | E72: Indicative (PJM preliminary, non-binding) | F72: PJM preliminary ELCC ratings (31 Aug 2026).
B73: Demand Resource ELCC class rating, 2037/38 | C73: 0.76 | D73: % | E73: Indicative (PJM preliminary, non-binding) | F73: PJM preliminary ELCC ratings (31 Aug 2026).
B74: Demand Resource ELCC class rating, 2038/39 | C74: 0.77 | D74: % | E74: Indicative (PJM preliminary, non-binding) | F74: PJM preliminary ELCC ratings (31 Aug 2026).
B75: Demand Resource ELCC class rating, 2039/40 | C75: 0.77 | D75: % | E75: Indicative (PJM preliminary, non-binding) | F75: PJM preliminary ELCC ratings (31 Aug 2026).
B76: Demand Resource ELCC class rating, 2040/41 | C76: 0.75 | D76: % | E76: Indicative (PJM preliminary, non-binding) | F76: PJM preliminary ELCC ratings (31 Aug 2026).
B77: Demand Resource ELCC class rating, 2041/42 | C77: 0.75 | D77: % | E77: Indicative (PJM preliminary, non-binding) | F77: PJM preliminary ELCC ratings (31 Aug 2026).
... B79: Demand Resource ELCC class rating, 2043/44 | C79: 0.75 | D79: % | E79: Held at last published value (judgment) | F79: Held at the 2042/43 value.
A81: K. Sensitivity ranges and benchmarks
B82: NREL normalized installed-cost factor, construction year 2028 (mid projection) | C82: 0.88 | D82: × 2024 cost | E82: Sourced | F82: NREL (2025) Table 2.
B83: Capacity price floor, 2029/30 RPM auctions | C83: 181.91 | D83: $/MW-day UCAP | E83: Sourced | F83: PJM 2029/30 planning parameters.
B84: Simulated uncollared capacity price (2028/29 BRA) | C84: 554.72 | D84: $/MW-day UCAP | E84: Sourced | F84: PJM 2028/29 BRA report, p.20.
B85: RBP maximum MW-weighted average procurement cost | C85: 555 | D85: $/MW-day UCAP | E85: Sourced | F85: PJM RBP filing ER26-3380.
B86: Fixed O&M under NREL's literal 4-hour definition | C86: =0.04*334*4/(C19*C59+C20) -> 0.019209202 | D86: % of NREL capital cost per yr | E86: Sourced; derived | F86: NREL (2025) p.11, Table 2.
B87: NREL cost factor, 2028 low projection | C87: 0.69 | D87: × 2024 cost | E87: Sourced | F87: NREL (2025) Table 2.
B88: NREL cost factor, 2028 high projection | C88: 1.08 | D88: × 2024 cost | E88: Sourced | F88: NREL (2025) Table 2.
B89: Investment tax credit without wage and apprenticeship rules | C89: 0.06 | D89: % | E89: Sourced | F89: IRS §48E.

Sheet Events
A1: PJM Demand-Response Dispatch Days in the Dominion Zone 1 Jan 2017 – 21 Sep 2026
A3: Source: PJM Emergency Procedures postings (column I); PJM Winter Storm Elliott report (Jul 2023).
A4: Date | B4: Event (highest action) | C4: Zones | D4: Cuts due | E4: Release | F4: Hours | G4: PAI (1 = yes) | H4: Winter (Nov–Apr) | I4: PJM postings | J4: Follows a dispatch day (1/0) | K4: Energy available at start (MWh) | L4: Energy delivered (MWh) | M4: Energy due but not delivered (MWh)
A5: 43740 | B5: Pre-Emergency DR; PAI | C5: AEP, BGE, DOM, PEPCO | D5: 0.58333333 | E5: 0.65625 | F5: =(E5-D5)*24 -> 1.75 | G5: 1 | H5: 0 | I5: EP 102663 | J5: 0 | K5: =Technical!$B$31 -> 500 | L5: =MIN(Technical!$B$30*F5,K5) -> 87.5 | M5: =Technical!$B$30*F5-L5 -> 0
A6: 44918 | B6: Winter Storm Elliott: Pre-Emergency and Emergency DR, EEA2; PAI | C6: PJM-wide | D6: 0.75 | E6: 0.92708333 | F6: =(E6-D6)*24 -> 4.25 | G6: 1 | H6: 1 | I6: EP 103783–103790 | J6: =IF(A6-A5=1,1,0) -> 0 | K6: =IF(AND(Sensitivity!$B$15=0,J6=1),MAX(0,K5-L5),Technical!$B$31) -> 500 | L6: =MIN(Technical!$B$30*F6,K6) -> 212.5 | M6: =Technical!$B$30*F6-L6 -> 0
A7: 44919 | B7: Winter Storm Elliott: all DR, EEA2, Max Gen Emergency Action; PAI | C7: PJM-wide | D7: 0.25 | E7: 0.85416667 | F7: =(E7-D7)*24 -> 14.5 | G7: 1 | H7: 1 | I7: EP 103798–103808 | J7: =IF(A7-A6=1,1,0) -> 1 | K7: =IF(AND(Sensitivity!$B$15=0,J7=1),MAX(0,K6-L6),Technical!$B$31) -> 500 | L7: =MIN(Technical!$B$30*F7,K7) -> 500 | M7: =Technical!$B$30*F7-L7 -> 225
A8: 45707 | B8: Pre-Emergency DR | C8: DOM Ashburn subzone | D8: 0.68055556 | E8: 0.92708333 | F8: =(E8-D8)*24 -> 5.9166667 | G8: 0 | H8: 1 | I8: EP 104514 | J8: =IF(A8-A7=1,1,0) -> 0 | K8: =IF(AND(Sensitivity!$B$15=0,J8=1),MAX(0,K7-L7),Technical!$B$31) -> 500 | L8: =MIN(Technical!$B$30*F8,K8) -> 295.83333 | M8: =Technical!$B$30*F8-L8 -> 0
A9: 45831 | B9: Pre-Emergency DR | C9: Mid-Atlantic and DOM | D9: 0.625 | E9: 0.91666667 | F9: =(E9-D9)*24 -> 7 | G9: 0 | H9: 0 | I9: EP 104654–104655 | J9: =IF(A9-A8=1,1,0) -> 0 | K9: =IF(AND(Sensitivity!$B$15=0,J9=1),MAX(0,K8-L8),Technical!$B$31) -> 500 | L9: =MIN(Technical!$B$30*F9,K9) -> 350 | M9: =Technical!$B$30*F9-L9 -> 0
A10: 45832 | B10: Pre-Emergency DR | C10: PJM-wide (19 zones) | D10: 0.625 | E10: 0.91666667 | F10: =(E10-D10)*24 -> 7 | G10: 0 | H10: 0 | I10: EP 104668–104669 | J10: =IF(A10-A9=1,1,0) -> 1 | K10: =IF(AND(Sensitivity!$B$15=0,J10=1),MAX(0,K9-L9),Technical!$B$31) -> 500 | L10: =MIN(Technical!$B$30*F10,K10) -> 350 | M10: =Technical!$B$30*F10-L10 -> 0
A11: 45833 | B11: Pre-Emergency DR | C11: Mid-Atlantic, DOM, APS | D11: 0.625 | E11: 0.79166667 | F11: =(E11-D11)*24 -> 4 | G11: 0 | H11: 0 | I11: EP 104686–104687 | J11: =IF(A11-A10=1,1,0) -> 1 | K11: =IF(AND(Sensitivity!$B$15=0,J11=1),MAX(0,K10-L10),Technical!$B$31) -> 500 | L11: =MIN(Technical!$B$30*F11,K11) -> 200 | M11: =Technical!$B$30*F11-L11 -> 0
A12: 45866 | B12: Pre-Emergency DR | C12: BGE, DOM, PEPCO | D12: 0.65625 | E12: 0.875 | F12: =(E12-D12)*24 -> 5.25 | G12: 0 | H12: 0 | I12: EP 104744 | J12: =IF(A12-A11=1,1,0) -> 0 | K12: =IF(AND(Sensitivity!$B$15=0,J12=1),MAX(0,K11-L11),Technical!$B$31) -> 500 | L12: =MIN(Technical!$B$30*F12,K12) -> 262.5 | M12: =Technical!$B$30*F12-L12 -> 0
A13: 45867 | B13: Pre-Emergency DR | C13: PJM-wide (19 zones) | D13: 0.58333333 | E13: 0.86458333 | F13: =(E13-D13)*24 -> 6.75 | G13: 0 | H13: 0 | I13: EP 104748 | J13: =IF(A13-A12=1,1,0) -> 1 | K13: =IF(AND(Sensitivity!$B$15=0,J13=1),MAX(0,K12-L12),Technical!$B$31) -> 500 | L13: =MIN(Technical!$B$30*F13,K13) -> 337.5 | M13: =Technical!$B$30*F13-L13 -> 0
A14: 46047 | B14: Pre-Emergency DR (Winter Storm Fern) | C14: BGE, DOM, PEPCO | D14: 0.60416667 | E14: 0.79166667 | F14: =(E14-D14)*24 -> 4.5 | G14: 0 | H14: 1 | I14: EP 104978–104980 | J14: =IF(A14-A13=1,1,0) -> 0 | K14: =IF(AND(Sensitivity!$B$15=0,J14=1),MAX(0,K13-L13),Technical!$B$31) -> 500 | L14: =MIN(Technical!$B$30*F14,K14) -> 225 | M14: =Technical!$B$30*F14-L14 -> 0
A15: 46160 | B15: Pre-Emergency DR | C15: BGE, DOM, PEPCO | D15: 0.625 | E15: 0.875 | F15: =(E15-D15)*24 -> 6 | G15: 0 | H15: 0 | I15: EP 105094–105098 | J15: =IF(A15-A14=1,1,0) -> 0 | K15: =IF(AND(Sensitivity!$B$15=0,J15=1),MAX(0,K14-L14),Technical!$B$31) -> 500 | L15: =MIN(Technical!$B$30*F15,K15) -> 300 | M15: =Technical!$B$30*F15-L15 -> 0
A16: 46161 | B16: Pre-Emergency DR | C16: BGE, DOM, PEPCO | D16: 0.58333333 | E16: 0.89583333 | F16: =(E16-D16)*24 -> 7.5 | G16: 0 | H16: 0 | I16: EP 105113–105117 | J16: =IF(A16-A15=1,1,0) -> 1 | K16: =IF(AND(Sensitivity!$B$15=0,J16=1),MAX(0,K15-L15),Technical!$B$31) -> 500 | L16: =MIN(Technical!$B$30*F16,K16) -> 375 | M16: =Technical!$B$30*F16-L16 -> 0
A17: 46205 | B17: Pre-Emergency and Emergency DR, EEA2 | C17: PJM-wide | D17: 0.5625 | E17: 0.89583333 | F17: =(E17-D17)*24 -> 8 | G17: 0 | H17: 0 | I17: EP 105291–105311 | J17: =IF(A17-A16=1,1,0) -> 0 | K17: =IF(AND(Sensitivity!$B$15=0,J17=1),MAX(0,K16-L16),Technical!$B$31) -> 500 | L17: =MIN(Technical!$B$30*F17,K17) -> 400 | M17: =Technical!$B$30*F17-L17 -> 0
... A20: 46282 | B20: Pre-Emergency and Emergency DR, EEA2 | C20: 10 zones incl. DOM | D20: 0.60416667 | E20: 0.91666667 | F20: =(E20-D20)*24 -> 7.5 | G20: 0 | H20: 0 | I20: EP 105532–105533 | J20: =IF(A20-A19=1,1,0) -> 0 | K20: =IF(AND(Sensitivity!$B$15=0,J20=1),MAX(0,K19-L19),Technical!$B$31) -> 500 | L20: =MIN(Technical!$B$30*F20,K20) -> 375 | M20: =Technical!$B$30*F20-L20 -> 0

Sheet Technical
A1: Technical Model
A3: 1. Service requirement (BYONC)
A4: New Large Load of the customer | B4: =Inputs!$C$12 -> 50 | C4: MW
A5: Forecast Pool Requirement | B5: =Inputs!$C$13 -> 0.9232 | C5: ratio
A6: BYONC requirement = load × FPR | B6: =B4*B5 -> 46.16 | C6: MW UCAP
A7: Battery power = new load (no export) | B7: =B4 -> 50 | C7: MW
A8: Accreditation, first delivery year (Demand Resource) | B8: =Inputs!$C$14 -> 0.9 | C8: %
A9: Accredited capacity (UCAP), first delivery year | B9: =B7*B8 -> 45 | C9: MW UCAP
A10: Share of BYONC requirement covered | B10: =B9/B6 -> 0.97487002 | C10: %
A11: BYONC shortfall = requirement − accredited capacity | B11: =B6-B9 -> 1.16 | C11: MW UCAP
A12: Accredited capacity if rated as 10-hour storage | B12: =$B$7*Inputs!$C$15 -> 38 | C12: MW UCAP
A13: Share of requirement covered at the storage rating | B13: =B12/$B$6 -> 0.82322357 | C13: %
A14: Shortfall at the storage rating | B14: =$B$6-B12 -> 8.16 | C14: MW UCAP
A15: Data center PUE (industry weighted average) | B15: =Inputs!$C$16 -> 1.54 | C15: ratio
A16: IT load protected by the service | B16: =$B$4/B15 -> 32.467532 | C16: MW IT
A18: 2. Dispatch record (Events sheet)
A19: Years in record | B19: =Inputs!$C$60 -> 9.72 | C19: years
A20: Demand-response days | B20: =COUNT(Events!$F$5:$F$20) -> 16 | C20: days
A21: Reduction hours in record | B21: =SUM(Events!$F$5:$F$20) -> 102.66667 | C21: hours
A22: Average reduction hours per year | B22: =B21/B19 -> 10.562414 | C22: hours/year
A23: Winter days (November–April) | B23: =SUM(Events!$H$5:$H$20) -> 4 | C23: days
A24: Longest event | B24: =MAX(Events!$F$5:$F$20) -> 14.5 | C24: hours
A26: 3. Sizing
A27: Design duration in use | B27: =Sensitivity!$B$11 -> 10 | C27: h
A28: Demand-response days fully covered | B28: =SUMPRODUCT(--(Events!$M$5:$M$20<0.001)) -> 15 | C28: days
A29: Share of days fully covered | B29: =B28/B20 -> 0.9375 | C29: %
A30: Battery power | B30: =$B$7 -> 50 | C30: MW
A31: Usable energy = power × duration | B31: =B30*B27 -> 500 | C31: MWh
A32: Battery power (kW) | B32: =$B$30*1000 -> 50000 | C32: kW
A33: Usable energy (kWh) | B33: =$B$31*1000 -> 500000 | C33: kWh
A34: Customer load under contract (kW) | B34: =$B$4*1000 -> 50000 | C34: kW
A36: 4. Event energy and PJM charges
A37: Energy delivered per year | B37: =SUM(Events!$L$5:$L$20)/B19 -> 504.97257 | C37: MWh/year
A38: Charging energy to restore it | B38: =B37/Inputs!$C$17 -> 594.08537 | C38: MWh/year
A39: Round-trip losses | B39: =B38-B37 -> 89.112806 | C39: MWh/year
A40: Energy due but not delivered, PAI days | B40: =SUMPRODUCT((Events!$G$5:$G$20=1)*Events!$M$5:$M$20)/B19 -> 23.148148 | C40: MWh/year
A41: Energy due but not delivered, other dispatch days | B41: =SUMPRODUCT((Events!$G$5:$G$20=0)*Events!$M$5:$M$20)/B19 -> 0 | C41: MWh/year
A42: Expected outage shortfall, PAI days | B42: =Inputs!$C$61*SUMPRODUCT((Events!$G$5:$G$20=1)*Events!$L$5:$L$20)/B19 -> 7.3580247 | C42: MWh/year
A43: Expected outage shortfall, other dispatch days | B43: =Inputs!$C$61*SUMPRODUCT((Events!$G$5:$G$20=0)*Events!$L$5:$L$20)/B19 -> 37.786523 | C43: MWh/year
A44: Non-performance charge rate = Net CONE × 365 ÷ 30 | B44: =Inputs!$C$62*365/30 -> 3185.1117 | C44: $/MWh
A45: Expected PJM performance charges | B45: =((B40+B42)*B44+(B41+B43)*B44*Inputs!$C$63)/10^6 -> 0.15734271 | C45: $M/year

Sheet Costs
A1: COSTS
A3: Capital cost
A4: (+) Energy component at the construction-year cost level (2024$) | B4: =Technical!$B$33*Inputs!$C$19*Sensitivity!$B$8/10^6 -> 106.04 | C4: $M
A5: (+) Power component at the construction-year cost level (2024$) | B5: =Technical!$B$32*Inputs!$C$20*Sensitivity!$B$8/10^6 -> 16.368 | C5: $M
A6: (=) NREL installed cost at the 2028 projection (2024$) | B6: =$B$4+$B$5 -> 122.408 | C6: $M
A7: Implied cost per usable kWh (2024$) | B7: =$B$6*10^6/Technical!$B$33 -> 244.816 | C7: $/kWh
A8: (×) Escalation factor, 2024 → construction year | B8: =(1+Inputs!$C$8)^(Inputs!$C$6-Inputs!$C$9) -> 1.1038129 | C8: x
A9: (=) Total CAPEX, construction-year dollars (Year 0) | B9: =$B$6*$B$8 -> 135.11553 | C9: $M
A10: Total CAPEX per kW | B10: =$B$9*10^6/Technical!$B$32 -> 2702.3106 | C10: $/kW
A11: Investment tax credit | B11: =Sensitivity!$B$13*$B$9 -> 40.534658 | C11: $M
A12: ITC cash proceeds (Year 1) | B12: =$B$11*Inputs!$C$22 -> 36.481193 | C12: $M
A13: Depreciable tax basis | B13: =$B$9-Inputs!$C$23*$B$11 -> 114.8482 | C13: $M
A15: Operating cost (Year 1 = first operating year, 2029/30)
A16: (+) Fixed O&M incl. augmentation, Year 1 | B16: =Sensitivity!$B$10*$B$6*(1+Inputs!$C$8)^(Inputs!$C$6+1-Inputs!$C$9) -> 5.5397367 | C16: $M/year
A17: (+) Property tax | B17: =Inputs!$C$27*$B$9 -> 1.1349704 | C17: $M/year
A18: (+) Insurance | B18: =Inputs!$C$26*$B$9 -> 0.54046211 | C18: $M/year
A19: (+) Charging losses, Year 1 | B19: =Technical!$B$39*Inputs!$C$28*(1+Inputs!$C$8)^(Inputs!$C$6+1-Inputs!$C$10)/10^6 -> 0.0046752344 | C19: $M/year
A20: (+) Expected PJM performance charges | B20: =Technical!$B$45 -> 0.15734271 | C20: $M/year
A21: (=) Operating cost, Year 1 | B21: =$B$16+$B$17+$B$18+$B$19+$B$20 -> 7.3771872 | C21: $M/year
A22: Tax and financing rates
A23: Combined income tax rate | B23: =Inputs!$C$37+Inputs!$C$38*(1-Inputs!$C$37) -> 0.2574 | C23: %
A24: Uncontracted (capacity) share of Year-1 revenue | B24: =1-CashFlow!$C$39 -> 0.25061535 | C24: %
A25: Merchant-revenue spread premium | B25: =IF($B$24>=Inputs!$C$52,Inputs!$C$51+Inputs!$C$53,IF($B$24>=Inputs!$C$50,Inputs!$C$51,0)) -> 0.0025 | C25: %
A26: (=) All-in debt interest rate | B26: =Sensitivity!$B$14+Inputs!$C$48+Inputs!$C$49+$B$25 -> 0.0702 | C26: %

Sheet CashFlow
A1: Cash Flow
A3: Year index | C3: 0 | D3: 1 | E3: 2 | F3: 3 | G3: 4 | H3: 5 | I3: 6 | J3: 7 | K3: 8 | L3: 9 | M3: 10 | N3: 11 | O3: 12 | P3: 13 | Q3: 14 | R3: 15
A4: PJM delivery year (June–May) | C4: =TEXT(Inputs!$C$6+C3,"0")&"/"&RIGHT(TEXT(Inputs!$C$6+C3+1,"0"),2) -> 2028/29 | D4: =TEXT(Inputs!$C$6+D3,"0")&"/"&RIGHT(TEXT(Inputs!$C$6+D3+1,"0"),2) -> 2029/30 | E4: =TEXT(Inputs!$C$6+E3,"0")&"/"&RIGHT(TEXT(Inputs!$C$6+E3+1,"0"),2) -> 2030/31 | F4: =TEXT(Inputs!$C$6+F3,"0")&"/"&RIGHT(TEXT(Inputs!$C$6+F3+1,"0"),2) -> 2031/32 | G4: =TEXT(Inputs!$C$6+G3,"0")&"/"&RIGHT(TEXT(Inputs!$C$6+G3+1,"0"),2) -> 2032/33 | H4: =TEXT(Inputs!$C$6+H3,"0")&"/"&RIGHT(TEXT(Inputs!$C$6+H3+1,"0"),2) -> 2033/34 | I4: =TEXT(Inputs!$C$6+I3,"0")&"/"&RIGHT(TEXT(Inputs!$C$6+I3+1,"0"),2) -> 2034/35 | J4: =TEXT(Inputs!$C$6+J3,"0")&"/"&RIGHT(TEXT(Inputs!$C$6+J3+1,"0"),2) -> 2035/36 | ... R4: =TEXT(Inputs!$C$6+R3,"0")&"/"&RIGHT(TEXT(Inputs!$C$6+R3+1,"0"),2) -> 2043/44
A5: Operating flag | B5: 1/0 | C5: =IF(AND(C3>=1,C3<=Inputs!$C$7),1,0) -> 0 | D5: =IF(AND(D3>=1,D3<=Inputs!$C$7),1,0) -> 1 | E5: =IF(AND(E3>=1,E3<=Inputs!$C$7),1,0) -> 1 | F5: =IF(AND(F3>=1,F3<=Inputs!$C$7),1,0) -> 1 | G5: =IF(AND(G3>=1,G3<=Inputs!$C$7),1,0) -> 1 | H5: =IF(AND(H3>=1,H3<=Inputs!$C$7),1,0) -> 1 | I5: =IF(AND(I3>=1,I3<=Inputs!$C$7),1,0) -> 1 | J5: =IF(AND(J3>=1,J3<=Inputs!$C$7),1,0) -> 1 | ... R5: =IF(AND(R3>=1,R3<=Inputs!$C$7),1,0) -> 1
A6: Debt service flag | B6: 1/0 | C6: =IF(AND(C3>=1,C3<=Inputs!$C$54),1,0) -> 0 | D6: =IF(AND(D3>=1,D3<=Inputs!$C$54),1,0) -> 1 | E6: =IF(AND(E3>=1,E3<=Inputs!$C$54),1,0) -> 1 | F6: =IF(AND(F3>=1,F3<=Inputs!$C$54),1,0) -> 1 | G6: =IF(AND(G3>=1,G3<=Inputs!$C$54),1,0) -> 1 | H6: =IF(AND(H3>=1,H3<=Inputs!$C$54),1,0) -> 1 | I6: =IF(AND(I3>=1,I3<=Inputs!$C$54),1,0) -> 1 | J6: =IF(AND(J3>=1,J3<=Inputs!$C$54),1,0) -> 1 | ... R6: =IF(AND(R3>=1,R3<=Inputs!$C$54),1,0) -> 1
A7: Accredited capacity (UCAP) | B7: MW | C7: =IF(C5=1,Technical!$B$7*INDEX(Inputs!$C$65:$C$79,C3),0) -> 0 | D7: =IF(D5=1,Technical!$B$7*INDEX(Inputs!$C$65:$C$79,D3),0) -> 45 | E7: =IF(E5=1,Technical!$B$7*INDEX(Inputs!$C$65:$C$79,E3),0) -> 42 | F7: =IF(F5=1,Technical!$B$7*INDEX(Inputs!$C$65:$C$79,F3),0) -> 41 | G7: =IF(G5=1,Technical!$B$7*INDEX(Inputs!$C$65:$C$79,G3),0) -> 41 | H7: =IF(H5=1,Technical!$B$7*INDEX(Inputs!$C$65:$C$79,H3),0) -> 40 | I7: =IF(I5=1,Technical!$B$7*INDEX(Inputs!$C$65:$C$79,I3),0) -> 39 | J7: =IF(J5=1,Technical!$B$7*INDEX(Inputs!$C$65:$C$79,J3),0) -> 38 | ... R7: =IF(R5=1,Technical!$B$7*INDEX(Inputs!$C$65:$C$79,R3),0) -> 37.5
A8: Revenue
A9: Customer load under contract | B9: kW | C9: =Technical!$B$34*C5 -> 0 | D9: =Technical!$B$34*D5 -> 50000 | E9: =Technical!$B$34*E5 -> 50000 | F9: =Technical!$B$34*F5 -> 50000 | G9: =Technical!$B$34*G5 -> 50000 | H9: =Technical!$B$34*H5 -> 50000 | I9: =Technical!$B$34*I5 -> 50000 | J9: =Technical!$B$34*J5 -> 50000 | ... R9: =Technical!$B$34*R5 -> 50000
A10: (+) Availability fee revenue | B10: $M | C10: =C9*Sensitivity!$B$12*(1+Inputs!$C$31)^(C3-1)*12/10^6 -> 0 | D10: =D9*Sensitivity!$B$12*(1+Inputs!$C$31)^(D3-1)*12/10^6 -> 16.592076 | E10: =E9*Sensitivity!$B$12*(1+Inputs!$C$31)^(E3-1)*12/10^6 -> 16.592076 | F10: =F9*Sensitivity!$B$12*(1+Inputs!$C$31)^(F3-1)*12/10^6 -> 16.592076 | G10: =G9*Sensitivity!$B$12*(1+Inputs!$C$31)^(G3-1)*12/10^6 -> 16.592076 | H10: =H9*Sensitivity!$B$12*(1+Inputs!$C$31)^(H3-1)*12/10^6 -> 16.592076 | I10: =I9*Sensitivity!$B$12*(1+Inputs!$C$31)^(I3-1)*12/10^6 -> 16.592076 | J10: =J9*Sensitivity!$B$12*(1+Inputs!$C$31)^(J3-1)*12/10^6 -> 16.592076 | ... R10: =R9*Sensitivity!$B$12*(1+Inputs!$C$31)^(R3-1)*12/10^6 -> 16.592076
A11: (+) PJM capacity revenue | B11: $M | C11: =C7*Sensitivity!$B$9*365*(1+Inputs!$C$33)^(C3-1)/10^6 -> 0 | D11: =D7*Sensitivity!$B$9*365*(1+Inputs!$C$33)^(D3-1)/10^6 -> 5.5488577 | E11: =E7*Sensitivity!$B$9*365*(1+Inputs!$C$33)^(E3-1)/10^6 -> 5.1789339 | F11: =F7*Sensitivity!$B$9*365*(1+Inputs!$C$33)^(F3-1)/10^6 -> 5.0556259 | G11: =G7*Sensitivity!$B$9*365*(1+Inputs!$C$33)^(G3-1)/10^6 -> 5.0556259 | H11: =H7*Sensitivity!$B$9*365*(1+Inputs!$C$33)^(H3-1)/10^6 -> 4.932318 | I11: =I7*Sensitivity!$B$9*365*(1+Inputs!$C$33)^(I3-1)/10^6 -> 4.80901 | J11: =J7*Sensitivity!$B$9*365*(1+Inputs!$C$33)^(J3-1)/10^6 -> 4.6857021 | ... R11: =R7*Sensitivity!$B$9*365*(1+Inputs!$C$33)^(R3-1)/10^6 -> 4.6240481
A12: (=) Total revenue | B12: $M | C12: =C10+C11 -> 0 | D12: =D10+D11 -> 22.140933 | E12: =E10+E11 -> 21.771009 | F12: =F10+F11 -> 21.647701 | G12: =G10+G11 -> 21.647701 | H12: =H10+H11 -> 21.524394 | I12: =I10+I11 -> 21.401086 | J12: =J10+J11 -> 21.277778 | ... R12: =R10+R11 -> 21.216124
A14: Operating cost
A15: (−) Fixed O&M incl. augmentation | B15: $M | C15: =-Costs!$B$16*(1+Inputs!$C$8)^(C3-1)*C5 -> 0 | D15: =-Costs!$B$16*(1+Inputs!$C$8)^(D3-1)*D5 -> -5.5397367 | E15: =-Costs!$B$16*(1+Inputs!$C$8)^(E3-1)*E5 -> -5.6782301 | F15: =-Costs!$B$16*(1+Inputs!$C$8)^(F3-1)*F5 -> -5.8201858 | G15: =-Costs!$B$16*(1+Inputs!$C$8)^(G3-1)*G5 -> -5.9656905 | H15: =-Costs!$B$16*(1+Inputs!$C$8)^(H3-1)*H5 -> -6.1148327 | I15: =-Costs!$B$16*(1+Inputs!$C$8)^(I3-1)*I5 -> -6.2677036 | J15: =-Costs!$B$16*(1+Inputs!$C$8)^(J3-1)*J5 -> -6.4243961 | ... R15: =-Costs!$B$16*(1+Inputs!$C$8)^(R3-1)*R5 -> -7.8275029
A16: (−) Property tax | B16: $M | C16: =-Costs!$B$17*C5 -> 0 | D16: =-Costs!$B$17*D5 -> -1.1349704 | E16: =-Costs!$B$17*E5 -> -1.1349704 | F16: =-Costs!$B$17*F5 -> -1.1349704 | G16: =-Costs!$B$17*G5 -> -1.1349704 | H16: =-Costs!$B$17*H5 -> -1.1349704 | I16: =-Costs!$B$17*I5 -> -1.1349704 | J16: =-Costs!$B$17*J5 -> -1.1349704 | ... R16: =-Costs!$B$17*R5 -> -1.1349704
A17: (−) Insurance | B17: $M | C17: =-Costs!$B$18*C5 -> 0 | D17: =-Costs!$B$18*D5 -> -0.54046211 | E17: =-Costs!$B$18*E5 -> -0.54046211 | F17: =-Costs!$B$18*F5 -> -0.54046211 | G17: =-Costs!$B$18*G5 -> -0.54046211 | H17: =-Costs!$B$18*H5 -> -0.54046211 | I17: =-Costs!$B$18*I5 -> -0.54046211 | J17: =-Costs!$B$18*J5 -> -0.54046211 | ... R17: =-Costs!$B$18*R5 -> -0.54046211
A18: (−) Charging losses | B18: $M | C18: =-Costs!$B$19*(1+Inputs!$C$8)^(C3-1)*C5 -> 0 | D18: =-Costs!$B$19*(1+Inputs!$C$8)^(D3-1)*D5 -> -0.0046752344 | E18: =-Costs!$B$19*(1+Inputs!$C$8)^(E3-1)*E5 -> -0.0047921153 | F18: =-Costs!$B$19*(1+Inputs!$C$8)^(F3-1)*F5 -> -0.0049119182 | G18: =-Costs!$B$19*(1+Inputs!$C$8)^(G3-1)*G5 -> -0.0050347161 | H18: =-Costs!$B$19*(1+Inputs!$C$8)^(H3-1)*H5 -> -0.005160584 | I18: =-Costs!$B$19*(1+Inputs!$C$8)^(I3-1)*I5 -> -0.0052895986 | J18: =-Costs!$B$19*(1+Inputs!$C$8)^(J3-1)*J5 -> -0.0054218386 | ... R18: =-Costs!$B$19*(1+Inputs!$C$8)^(R3-1)*R5 -> -0.0066059839
A19: (−) Expected PJM performance charges | B19: $M | C19: =-Costs!$B$20*C5 -> 0 | D19: =-Costs!$B$20*D5 -> -0.15734271 | E19: =-Costs!$B$20*E5 -> -0.15734271 | F19: =-Costs!$B$20*F5 -> -0.15734271 | G19: =-Costs!$B$20*G5 -> -0.15734271 | H19: =-Costs!$B$20*H5 -> -0.15734271 | I19: =-Costs!$B$20*I5 -> -0.15734271 | J19: =-Costs!$B$20*J5 -> -0.15734271 | ... R19: =-Costs!$B$20*R5 -> -0.15734271
A20: (=) Total operating cost | B20: $M | C20: =SUM(C15:C19) -> 0 | D20: =SUM(D15:D19) -> -7.3771872 | E20: =SUM(E15:E19) -> -7.5157975 | F20: =SUM(F15:F19) -> -7.657873 | G20: =SUM(G15:G19) -> -7.8035005 | H20: =SUM(H15:H19) -> -7.9527686 | I20: =SUM(I15:I19) -> -8.1057684 | J20: =SUM(J15:J19) -> -8.2625932 | ... R20: =SUM(R15:R19) -> -9.6668841
A21: (=) EBITDA | B21: $M | C21: =C12+C20 -> 0 | D21: =D12+D20 -> 14.763746 | E21: =E12+E20 -> 14.255212 | F21: =F12+F20 -> 13.989828 | G21: =G12+G20 -> 13.844201 | H21: =H12+H20 -> 13.571625 | I21: =I12+I20 -> 13.295317 | J21: =J12+J20 -> 13.015184 | ... R21: =R12+R20 -> 11.54924
A22: Capital and incentives
A23: (−) CAPEX | B23: $M | C23: =-Costs!$B$9*(C3=0) -> -135.11553 | D23: =-Costs!$B$9*(D3=0) -> 0 | E23: =-Costs!$B$9*(E3=0) -> 0 | F23: =-Costs!$B$9*(F3=0) -> 0 | G23: =-Costs!$B$9*(G3=0) -> 0 | H23: =-Costs!$B$9*(H3=0) -> 0 | I23: =-Costs!$B$9*(I3=0) -> 0 | J23: =-Costs!$B$9*(J3=0) -> 0 | ... R23: =-Costs!$B$9*(R3=0) -> 0
A24: (+) ITC cash proceeds | B24: $M | C24: =Costs!$B$12*(C3=1) -> 0 | D24: =Costs!$B$12*(D3=1) -> 36.481193 | E24: =Costs!$B$12*(E3=1) -> 0 | F24: =Costs!$B$12*(F3=1) -> 0 | G24: =Costs!$B$12*(G3=1) -> 0 | H24: =Costs!$B$12*(H3=1) -> 0 | I24: =Costs!$B$12*(I3=1) -> 0 | J24: =Costs!$B$12*(J3=1) -> 0 | ... R24: =Costs!$B$12*(R3=1) -> 0
A26: Unlevered tax (project view)
A27: MACRS rate | B27: % | C27: =IF(AND(C3>=1,C3<=6),INDEX(Inputs!$C$40:$C$45,C3),0) -> 0 | D27: =IF(AND(D3>=1,D3<=6),INDEX(Inputs!$C$40:$C$45,D3),0) -> 0.2 | E27: =IF(AND(E3>=1,E3<=6),INDEX(Inputs!$C$40:$C$45,E3),0) -> 0.32 | F27: =IF(AND(F3>=1,F3<=6),INDEX(Inputs!$C$40:$C$45,F3),0) -> 0.192 | G27: =IF(AND(G3>=1,G3<=6),INDEX(Inputs!$C$40:$C$45,G3),0) -> 0.1152 | H27: =IF(AND(H3>=1,H3<=6),INDEX(Inputs!$C$40:$C$45,H3),0) -> 0.1152 | I27: =IF(AND(I3>=1,I3<=6),INDEX(Inputs!$C$40:$C$45,I3),0) -> 0.0576 | J27: =IF(AND(J3>=1,J3<=6),INDEX(Inputs!$C$40:$C$45,J3),0) -> 0 | ... R27: =IF(AND(R3>=1,R3<=6),INDEX(Inputs!$C$40:$C$45,R3),0) -> 0
A28: (−) Tax depreciation | B28: $M | C28: =-Costs!$B$13*C27 -> 0 | D28: =-Costs!$B$13*D27 -> -22.96964 | E28: =-Costs!$B$13*E27 -> -36.751424 | F28: =-Costs!$B$13*F27 -> -22.050854 | G28: =-Costs!$B$13*G27 -> -13.230513 | H28: =-Costs!$B$13*H27 -> -13.230513 | I28: =-Costs!$B$13*I27 -> -6.6152563 | J28: =-Costs!$B$13*J27 -> 0 | ... R28: =-Costs!$B$13*R27 -> 0
A29: (=) Taxable income before losses | B29: $M | C29: =C21+C28 -> 0 | D29: =D21+D28 -> -8.2058937 | E29: =E21+E28 -> -22.496212 | F29: =F21+F28 -> -8.0610258 | G29: =G21+G28 -> 0.61368846 | H29: =H21+H28 -> 0.34111238 | I29: =I21+I28 -> 6.6800609 | J29: =J21+J28 -> 13.015184 | ... R29: =R21+R28 -> 11.54924
A30: Loss carryforward, opening | B30: $M | C30: 0 | D30: =C33 -> 0 | E30: =D33 -> 8.2058937 | F30: =E33 -> 30.702105 | G30: =F33 -> 38.763131 | H30: =G33 -> 38.27218 | I30: =H33 -> 37.999291 | J30: =I33 -> 32.655242 | K30: =J33 -> 22.243094 | ... R30: =Q33 -> 0
A31: Loss used | B31: $M | C31: =MIN(C30,Inputs!$C$39*MAX(0,C29)) -> 0 | D31: =MIN(D30,Inputs!$C$39*MAX(0,D29)) -> 0 | E31: =MIN(E30,Inputs!$C$39*MAX(0,E29)) -> 0 | F31: =MIN(F30,Inputs!$C$39*MAX(0,F29)) -> 0 | G31: =MIN(G30,Inputs!$C$39*MAX(0,G29)) -> 0.49095077 | H31: =MIN(H30,Inputs!$C$39*MAX(0,H29)) -> 0.27288991 | I31: =MIN(I30,Inputs!$C$39*MAX(0,I29)) -> 5.3440487 | J31: =MIN(J30,Inputs!$C$39*MAX(0,J29)) -> 10.412147 | ... R31: =MIN(R30,Inputs!$C$39*MAX(0,R29)) -> 0
A32: (=) Taxable income after losses | B32: $M | C32: =MAX(0,C29)-C31 -> 0 | D32: =MAX(0,D29)-D31 -> 0 | E32: =MAX(0,E29)-E31 -> 0 | F32: =MAX(0,F29)-F31 -> 0 | G32: =MAX(0,G29)-G31 -> 0.12273769 | H32: =MAX(0,H29)-H31 -> 0.068222477 | I32: =MAX(0,I29)-I31 -> 1.3360122 | J32: =MAX(0,J29)-J31 -> 2.6030369 | ... R32: =MAX(0,R29)-R31 -> 11.54924
A33: Loss carryforward, closing | B33: $M | C33: =C30-C31+MAX(0,-C29) -> 0 | D33: =D30-D31+MAX(0,-D29) -> 8.2058937 | E33: =E30-E31+MAX(0,-E29) -> 30.702105 | F33: =F30-F31+MAX(0,-F29) -> 38.763131 | G33: =G30-G31+MAX(0,-G29) -> 38.27218 | H33: =H30-H31+MAX(0,-H29) -> 37.999291 | I33: =I30-I31+MAX(0,-I29) -> 32.655242 | J33: =J30-J31+MAX(0,-J29) -> 22.243094 | ... R33: =R30-R31+MAX(0,-R29) -> 0
A34: (−) Unlevered income tax | B34: $M | C34: =-Costs!$B$23*C32 -> 0 | D34: =-Costs!$B$23*D32 -> 0 | E34: =-Costs!$B$23*E32 -> 0 | F34: =-Costs!$B$23*F32 -> 0 | G34: =-Costs!$B$23*G32 -> -0.031592682 | H34: =-Costs!$B$23*H32 -> -0.017560465 | I34: =-Costs!$B$23*I32 -> -0.34388953 | J34: =-Costs!$B$23*J32 -> -0.67002169 | ... R34: =-Costs!$B$23*R32 -> -2.9727742
A36: (=) Project cash flow | B36: $M | C36: =C21+C34+C23+C24 -> -135.11553 | D36: =D21+D34+D23+D24 -> 51.244939 | E36: =E21+E34+E23+E24 -> 14.255212 | F36: =F21+F34+F23+F24 -> 13.989828 | G36: =G21+G34+G23+G24 -> 13.812608 | H36: =H21+H34+H23+H24 -> 13.554064 | I36: =I21+I34+I23+I24 -> 12.951428 | J36: =J21+J34+J23+J24 -> 12.345163 | ... R36: =R21+R34+R23+R24 -> 8.5764653
A38: Debt sizing
A39: Contracted (fee) share of Year-1 revenue | B39: % | C39: =D10/D12 -> 0.74938465
A40: Blended DSCR target | B40: x | C40: =C39*Inputs!$C$55+(1-C39)*Inputs!$C$56 -> 1.4004923
A41: Sizing CFADS | B41: $M | C41: =IF(C6=1,C21+C34,"") | D41: =IF(D6=1,D21+D34,"") -> 14.763746 | E41: =IF(E6=1,E21+E34,"") -> 14.255212 | F41: =IF(F6=1,F21+F34,"") -> 13.989828 | G41: =IF(G6=1,G21+G34,"") -> 13.812608 | H41: =IF(H6=1,H21+H34,"") -> 13.554064 | I41: =IF(I6=1,I21+I34,"") -> 12.951428 | J41: =IF(J6=1,J21+J34,"") -> 12.345163 | ... R41: =IF(R6=1,R21+R34,"") -> 8.5764653
A42: Minimum sizing CFADS | B42: $M | C42: =MIN(C41:R41) -> 8.5764653
A43: Level annual debt service | B43: $M | C43: =C42/C40 -> 6.1238933
A44: Debt raised | B44: $M | C44: =PV(Costs!$B$26,Inputs!$C$54,-C43) -> 55.705504
A45: Opening balance | B45: $M | C45: 0 | D45: =C49 -> 55.705504 | E45: =D49 -> 53.492137 | F45: =E49 -> 51.123391 | G45: =F49 -> 48.58836 | H45: =G49 -> 45.87537 | I45: =H49 -> 42.971928 | J45: =I49 -> 39.864664 | K45: =J49 -> 36.53927 | ... R45: =Q49 -> 5.7221952
A46: (+) Debt draw | B46: $M | C46: =$C$44*(C3=0) -> 55.705504 | D46: =$C$44*(D3=0) -> 0 | E46: =$C$44*(E3=0) -> 0 | F46: =$C$44*(F3=0) -> 0 | G46: =$C$44*(G3=0) -> 0 | H46: =$C$44*(H3=0) -> 0 | I46: =$C$44*(I3=0) -> 0 | J46: =$C$44*(J3=0) -> 0 | ... R46: =$C$44*(R3=0) -> 0
A47: (−) Interest | B47: $M | C47: =-C45*Costs!$B$26*C6 -> 0 | D47: =-D45*Costs!$B$26*D6 -> -3.9105264 | E47: =-E45*Costs!$B$26*E6 -> -3.755148 | F47: =-F45*Costs!$B$26*F6 -> -3.5888621 | G47: =-G45*Costs!$B$26*G6 -> -3.4109029 | H47: =-H45*Costs!$B$26*H6 -> -3.220451 | I47: =-I45*Costs!$B$26*I6 -> -3.0166293 | J47: =-J45*Costs!$B$26*J6 -> -2.7984994 | ... R47: =-R45*Costs!$B$26*R6 -> -0.4016981
A48: (−) Principal | B48: $M | C48: =C50-C47 -> 0 | D48: =D50-D47 -> -2.2133669 | E48: =E50-E47 -> -2.3687453 | F48: =F50-F47 -> -2.5350312 | G48: =G50-G47 -> -2.7129904 | H48: =H50-H47 -> -2.9034423 | I48: =I50-I47 -> -3.107264 | J48: =J50-J47 -> -3.3253939 | ... R48: =R50-R47 -> -5.7221952
A49: Closing balance | B49: $M | C49: =C45+C46+C48 -> 55.705504 | D49: =D45+D46+D48 -> 53.492137 | E49: =E45+E46+E48 -> 51.123391 | F49: =F45+F46+F48 -> 48.58836 | G49: =G45+G46+G48 -> 45.87537 | H49: =H45+H46+H48 -> 42.971928 | I49: =I45+I46+I48 -> 39.864664 | J49: =J45+J46+J48 -> 36.53927 | ... R49: =R45+R46+R48 -> 2.7533531e-14
A50: (−) Debt service | B50: $M | C50: =-$C$43*C6 -> 0 | D50: =-$C$43*D6 -> -6.1238933 | E50: =-$C$43*E6 -> -6.1238933 | F50: =-$C$43*F6 -> -6.1238933 | G50: =-$C$43*G6 -> -6.1238933 | H50: =-$C$43*H6 -> -6.1238933 | I50: =-$C$43*I6 -> -6.1238933 | J50: =-$C$43*J6 -> -6.1238933 | ... R50: =-$C$43*R6 -> -6.1238933
A52: Levered tax (equity view)
A53: (=) Taxable income before losses | B53: $M | C53: =C21+C28+C47 -> 0 | D53: =D21+D28+D47 -> -12.11642 | E53: =E21+E28+E47 -> -26.25136 | F53: =F21+F28+F47 -> -11.649888 | G53: =G21+G28+G47 -> -2.7972144 | H53: =H21+H28+H47 -> -2.8793386 | I53: =I21+I28+I47 -> 3.6634315 | J53: =J21+J28+J47 -> 10.216685 | ... R53: =R21+R28+R47 -> 11.147541
A54: Loss carryforward, opening | B54: $M | C54: 0 | D54: =C57 -> 0 | E54: =D57 -> 12.11642 | F54: =E57 -> 38.36778 | G54: =F57 -> 50.017668 | H54: =G57 -> 52.814882 | I54: =H57 -> 55.694221 | J54: =I57 -> 52.763475 | K54: =J57 -> 44.590128 | ... R54: =Q57 -> 0
A55: Loss used | B55: $M | C55: =MIN(C54,Inputs!$C$39*MAX(0,C53)) -> 0 | D55: =MIN(D54,Inputs!$C$39*MAX(0,D53)) -> 0 | E55: =MIN(E54,Inputs!$C$39*MAX(0,E53)) -> 0 | F55: =MIN(F54,Inputs!$C$39*MAX(0,F53)) -> 0 | G55: =MIN(G54,Inputs!$C$39*MAX(0,G53)) -> 0 | H55: =MIN(H54,Inputs!$C$39*MAX(0,H53)) -> 0 | I55: =MIN(I54,Inputs!$C$39*MAX(0,I53)) -> 2.9307452 | J55: =MIN(J54,Inputs!$C$39*MAX(0,J53)) -> 8.173348 | ... R55: =MIN(R54,Inputs!$C$39*MAX(0,R53)) -> 0
A56: (=) Taxable income after losses | B56: $M | C56: =MAX(0,C53)-C55 -> 0 | D56: =MAX(0,D53)-D55 -> 0 | E56: =MAX(0,E53)-E55 -> 0 | F56: =MAX(0,F53)-F55 -> 0 | G56: =MAX(0,G53)-G55 -> 0 | H56: =MAX(0,H53)-H55 -> 0 | I56: =MAX(0,I53)-I55 -> 0.73268631 | J56: =MAX(0,J53)-J55 -> 2.043337 | ... R56: =MAX(0,R53)-R55 -> 11.147541
A57: Loss carryforward, closing | B57: $M | C57: =C54-C55+MAX(0,-C53) -> 0 | D57: =D54-D55+MAX(0,-D53) -> 12.11642 | E57: =E54-E55+MAX(0,-E53) -> 38.36778 | F57: =F54-F55+MAX(0,-F53) -> 50.017668 | G57: =G54-G55+MAX(0,-G53) -> 52.814882 | H57: =H54-H55+MAX(0,-H53) -> 55.694221 | I57: =I54-I55+MAX(0,-I53) -> 52.763475 | J57: =J54-J55+MAX(0,-J53) -> 44.590128 | ... R57: =R54-R55+MAX(0,-R53) -> 0
A58: (−) Levered income tax | B58: $M | C58: =-Costs!$B$23*C56 -> 0 | D58: =-Costs!$B$23*D56 -> 0 | E58: =-Costs!$B$23*E56 -> 0 | F58: =-Costs!$B$23*F56 -> 0 | G58: =-Costs!$B$23*G56 -> 0 | H58: =-Costs!$B$23*H56 -> 0 | I58: =-Costs!$B$23*I56 -> -0.18859346 | J58: =-Costs!$B$23*J56 -> -0.52595494 | ... R58: =-Costs!$B$23*R56 -> -2.8693772
A60: Coverage and equity
A61: (=) CFADS | B61: $M | C61: =(C21+C58)*C5 -> 0 | D61: =(D21+D58)*D5 -> 14.763746 | E61: =(E21+E58)*E5 -> 14.255212 | F61: =(F21+F58)*F5 -> 13.989828 | G61: =(G21+G58)*G5 -> 13.844201 | H61: =(H21+H58)*H5 -> 13.571625 | I61: =(I21+I58)*I5 -> 13.106724 | J61: =(J21+J58)*J5 -> 12.489229 | ... R61: =(R21+R58)*R5 -> 8.6798623
A62: DSCR | B62: x | C62: =IF(C6=1,C61/-C50,"") | D62: =IF(D6=1,D61/-D50,"") -> 2.4108431 | E62: =IF(E6=1,E61/-E50,"") -> 2.3278022 | F62: =IF(F6=1,F61/-F50,"") -> 2.2844664 | G62: =IF(G6=1,G61/-G50,"") -> 2.2606862 | H62: =IF(H6=1,H61/-H50,"") -> 2.2161759 | I62: =IF(I6=1,I61/-I50,"") -> 2.14026 | J62: =IF(J6=1,J61/-J50,"") -> 2.0394264 | ... R62: =IF(R6=1,R61/-R50,"") -> 1.4173765
A64: (=) Equity cash flow | B64: $M | C64: =C23+C46 -> -79.410025 | D64: =D61+D50+D24 -> 45.121045 | E64: =E61+E50+E24 -> 8.1313187 | F64: =F61+F50+F24 -> 7.8659352 | G64: =G61+G50+G24 -> 7.7203077 | H64: =H61+H50+H24 -> 7.4477316 | I64: =I61+I50+I24 -> 6.9828304 | J64: =J61+J50+J24 -> 6.3653361 | K64: =K61+K50+K24 -> 6.1423682 | ... R64: =R61+R50+R24 -> 2.5559691
A65: Cumulative equity cash flow | B65: $M | C65: =C64 -> -79.410025 | D65: =C65+D64 -> -34.288979 | E65: =D65+E64 -> -26.15766 | F65: =E65+F64 -> -18.291725 | G65: =F65+G64 -> -10.571418 | H65: =G65+H64 -> -3.123686 | I65: =H65+I64 -> 3.8591444 | J65: =I65+J64 -> 10.224481 | K65: =J65+K64 -> 16.366849 | ... R65: =Q65+R64 -> 48.541581
A66: Cumulative project cash flow | B66: $M | C66: =C36 -> -135.11553 | D66: =C66+D36 -> -83.87059 | E66: =D66+E36 -> -69.615378 | F66: =E66+F36 -> -55.625549 | G66: =F66+G36 -> -41.812941 | H66: =G66+H36 -> -28.258876 | I66: =H66+I36 -> -15.307449 | J66: =I66+J36 -> -2.9622862 | K66: =J66+K36 -> 9.1719262 | ... R66: =Q66+R36 -> 75.388721

Sheet Results
A1: RESULTS
A3: Configuration and output
A4: Battery power | B4: =Technical!$B$30 -> 50 | C4: MW
A5: Usable energy | B5: =Technical!$B$31 -> 500 | C5: MWh
A6: Accredited capacity (UCAP) | B6: =Technical!$B$9 -> 45 | C6: MW UCAP
A7: Share of BYONC requirement covered | B7: =Technical!$B$10 -> 0.97487002 | C7: %
A8: Costs, revenue and funding
A9: Minimum battery service fee (solved) | B9: =Inputs!$C$30 -> 27.653459 | C9: $/kW-month
A10: Total CAPEX | B10: =Costs!$B$9 -> 135.11553 | C10: $M
A11: ITC cash proceeds | B11: =Costs!$B$12 -> 36.481193 | C11: $M
A12: Operating cost, Year 1 | B12: =-CashFlow!$D$20 -> 7.3771872 | C12: $M
A13: Fee revenue, Year 1 | B13: =CashFlow!$D$10 -> 16.592076 | C13: $M
A14: Capacity revenue, Year 1 | B14: =CashFlow!$D$11 -> 5.5488577 | C14: $M
A15: Total revenue, Year 1 | B15: =CashFlow!$D$12 -> 22.140933 | C15: $M
A16: Capacity (uncontracted) share of Year-1 revenue | B16: =Costs!$B$24 -> 0.25061535 | C16: %
A17: All-in debt interest rate | B17: =Costs!$B$26 -> 0.0702 | C17: %
A18: Minimum sizing CFADS | B18: =CashFlow!$C$42 -> 8.5764653 | C18: $M
A19: Debt raised | B19: =CashFlow!$C$44 -> 55.705504 | C19: $M
A20: Gearing (debt ÷ CAPEX) | B20: =$B$19/$B$10 -> 0.41228055 | C20: %
A21: Equity contribution | B21: =$B$10-$B$19 -> 79.410025 | C21: $M
A22: Financial performance
A23: Equity NPV at target equity return | B23: =CashFlow!$C$64+NPV(Inputs!$C$57,CashFlow!$D$64:$R$64) -> -3.6346341e-06 | C23: $M
A24: Equity IRR | B24: =IRR(CashFlow!$C$64:$R$64) -> 0.11999999 | C24: %
A25: Project IRR (unlevered, after tax) | B25: =IRR(CashFlow!$C$36:$R$36) -> 0.086760085 | C25: %
A26: Minimum DSCR | B26: =MIN(CashFlow!$C$62:$R$62) -> 1.4173765 | C26: x
A27: Blended DSCR target | B27: =CashFlow!$C$40 -> 1.4004923 | C27: x
A28: Customer value
A29: IT capacity of the load | B29: =Technical!$B$16 -> 32.467532 | C29: MW IT
A30: Colocation rent of that IT capacity | B30: =Technical!$B$16*1000*Inputs!$C$35*12/10^6 -> 62.337662 | C30: $M/year
A31: Year-1 fee as share of that rent | B31: =$B$13/$B$30 -> 0.26616454 | C31: %
A33: Design basis and PJM performance risk
A34: Design duration | B34: =Technical!$B$27 -> 10 | C34: h
A35: Dominion demand-response days fully covered | B35: =Technical!$B$28 -> 15 | C35: days
A36: Expected PJM performance charges | B36: =Costs!$B$20 -> 0.15734271 | C36: $M/year
A38: Model checks
A39: Equity NPV at 12% (0 once Goal Seek is current) | B39: =$B$23 -> -3.6346341e-06 | C39: =IF(ABS(B39)<0.001,"OK","Re-run Goal Seek") -> OK
A40: Debt balance after Year 15 (should be 0) | B40: =CashFlow!$R$49 -> 2.7533531e-14 | C40: =IF(ABS(B40)<0.001,"OK","Debt not repaid") -> OK
A41: Minimum DSCR minus lender target (should be 0 or more) | B41: =$B$26-$B$27 -> 0.016884209 | C41: =IF(B41>=0,"OK","Below target") -> OK
A43: Additional metrics
A44: Average DSCR | B44: =AVERAGE(CashFlow!$D$62:$R$62) -> 1.9957763 | C44: x
A45: Equity payback, operating year | B45: =MATCH(TRUE,INDEX(CashFlow!$D$65:$R$65>=0,0),0) -> 6 | C45: year
A46: Equity payback, delivery year | B46: =INDEX(CashFlow!$D$4:$R$4,B45) -> 2034/35
A47: Project payback, operating year | B47: =MATCH(TRUE,INDEX(CashFlow!$D$66:$R$66>=0,0),0) -> 8 | C47: year
A48: Project payback, delivery year | B48: =INDEX(CashFlow!$D$4:$R$4,B47) -> 2036/37
A49: First year with income tax, operating year | B49: =MATCH(TRUE,INDEX(CashFlow!$D$58:$R$58<0,0),0) -> 6 | C49: year
A50: First year with income tax, delivery year | B50: =INDEX(CashFlow!$D$4:$R$4,B49) -> 2034/35
A51: Project NPV at the debt rate | B51: =CashFlow!$C$36+NPV(Costs!$B$26,CashFlow!$D$36:$R$36) -> 10.172972 | C51: $M
A52: Fee per accredited MW-day | B52: =Customer!$B$17 -> 1010.172 | C52: $/MW-day
A53: EBITDA margin, Year 1 | B53: =CashFlow!$D$21/CashFlow!$D$12 -> 0.66680776 | C53: %
A54: EBITDA margin, Year 15 | B54: =CashFlow!$R$21/CashFlow!$R$12 -> 0.54436143 | C54: %
A55: DSCR, Year 1 | B55: =CashFlow!$D$62 -> 2.4108431 | C55: x
A56: DSCR, Year 15 | B56: =CashFlow!$R$62 -> 1.4173765 | C56: x
A57: Level annual debt service | B57: =CashFlow!$C$43 -> 6.1238933 | C57: $M/year
A59: 15-year totals (Years 1–15)
A60: Fee revenue | B60: =SUM(CashFlow!$D$10:$R$10) -> 248.88113 | C60: $M
A61: Capacity revenue | B61: =SUM(CashFlow!$D$11:$R$11) -> 72.566729 | C61: $M
A62: Total revenue | B62: =SUM(CashFlow!$D$12:$R$12) -> 321.44786 | C62: $M
A63: Operating cost | B63: =-SUM(CashFlow!$D$20:$R$20) -> 126.91362 | C63: $M
A64: Income tax | B64: =-SUM(CashFlow!$D$58:$R$58) -> 11.205433 | C64: $M
A65: Debt service | B65: =-SUM(CashFlow!$D$50:$R$50) -> 91.858399 | C65: $M
A66: Cash to equity from operations (excl. tax credit) | B66: =SUM(CashFlow!$D$64:$R$64)-Costs!$B$12 -> 91.470413 | C66: $M
A67: Tax credit proceeds | B67: =Costs!$B$12 -> 36.481193 | C67: $M
A68: Share of revenue: operating cost | B68: =B63/B62 -> 0.39481867 | C68: %
A69: Share of revenue: debt service | B69: =B65/B62 -> 0.28576454 | C69: %
A70: Share of revenue: income tax | B70: =B64/B62 -> 0.034859255 | C70: %
A71: Share of revenue: cash to equity | B71: =B66/B62 -> 0.28455754 | C71: %

Sheet Sensitivity
A1: Sensitivity
A5: Active case
A6: Case number (blank = base case)
A7: Trial fee, $/kW-month (blank = solved fee on Inputs)
A8: NREL cost factor in use | B8: =IF($B$16<>"",$B$16,IF($B$6="",Inputs!$C$82,INDEX($B$20:$B$32,$B$6))) -> 0.88
A9: Capacity price in use ($/MW-day) | B9: =IF($B$6="",Inputs!$C$32,INDEX($C$20:$C$32,$B$6)) -> 337.83
A10: Fixed O&M rate in use (% of cost) | B10: =IF($B$6="",Inputs!$C$25,INDEX($D$20:$D$32,$B$6)) -> 0.04
A11: Design duration in use (h) | B11: =IF($B$6="",Inputs!$C$59,INDEX($E$20:$E$32,$B$6)) -> 10
A12: Fee in use ($/kW-month) | B12: =IF($B$7="",Inputs!$C$30,$B$7) -> 27.653459
A13: Tax-credit rate in use | B13: =IF($B$6="",Inputs!$C$21,INDEX($F$20:$F$32,$B$6)) -> 0.3
A14: Treasury base rate in use | B14: =IF($B$6="",Inputs!$C$47,INDEX($G$20:$G$32,$B$6)) -> 0.0477
A15: Overnight recharge between consecutive dispatch days (1 = yes) | B15: =IF($B$6="",1,INDEX($H$20:$H$32,$B$6)) -> 1
A16: NREL cost factor override (blank; used only by the threshold Data Table)
A18: Cases
A19: Case | B19: NREL cost factor | C19: Capacity price ($/MW-day) | D19: Fixed O&M (% of cost) | E19: Duration (h) | F19: Tax-credit rate | G19: Treasury base rate | H19: Overnight recharge (1/0)
A20: 1 Base case | B20: =Inputs!$C$82 -> 0.88 | C20: =Inputs!$C$32 -> 337.83 | D20: =Inputs!$C$25 -> 0.04 | E20: =Inputs!$C$59 -> 10 | F20: =Inputs!$C$21 -> 0.3 | G20: =Inputs!$C$47 -> 0.0477 | H20: 1
A21: 2 Installed cost: NREL 2028 low | B21: =Inputs!$C$87 -> 0.69 | C21: =Inputs!$C$32 -> 337.83 | D21: =Inputs!$C$25 -> 0.04 | E21: =Inputs!$C$59 -> 10 | F21: =Inputs!$C$21 -> 0.3 | G21: =Inputs!$C$47 -> 0.0477 | H21: 1
A22: 3 Installed cost: NREL 2028 high | B22: =Inputs!$C$88 -> 1.08 | C22: =Inputs!$C$32 -> 337.83 | D22: =Inputs!$C$25 -> 0.04 | E22: =Inputs!$C$59 -> 10 | F22: =Inputs!$C$21 -> 0.3 | G22: =Inputs!$C$47 -> 0.0477 | H22: 1
A23: 4 Capacity price: 2029/30 floor | B23: =Inputs!$C$82 -> 0.88 | C23: =Inputs!$C$83 -> 181.91 | D23: =Inputs!$C$25 -> 0.04 | E23: =Inputs!$C$59 -> 10 | F23: =Inputs!$C$21 -> 0.3 | G23: =Inputs!$C$47 -> 0.0477 | H23: 1
A24: 5 Capacity price: uncollared | B24: =Inputs!$C$82 -> 0.88 | C24: =Inputs!$C$84 -> 554.72 | D24: =Inputs!$C$25 -> 0.04 | E24: =Inputs!$C$59 -> 10 | F24: =Inputs!$C$21 -> 0.3 | G24: =Inputs!$C$47 -> 0.0477 | H24: 1
A25: 6 Fixed O&M: NREL literal | B25: =Inputs!$C$82 -> 0.88 | C25: =Inputs!$C$32 -> 337.83 | D25: =Inputs!$C$86 -> 0.019209202 | E25: =Inputs!$C$59 -> 10 | F25: =Inputs!$C$21 -> 0.3 | G25: =Inputs!$C$47 -> 0.0477 | H25: 1
A26: 7 Duration 5 h | B26: =Inputs!$C$82 -> 0.88 | C26: =Inputs!$C$32 -> 337.83 | D26: =Inputs!$C$25 -> 0.04 | E26: 5 | F26: =Inputs!$C$21 -> 0.3 | G26: =Inputs!$C$47 -> 0.0477 | H26: 1
A27: 8 Duration 15 h | B27: =Inputs!$C$82 -> 0.88 | C27: =Inputs!$C$32 -> 337.83 | D27: =Inputs!$C$25 -> 0.04 | E27: 15 | F27: =Inputs!$C$21 -> 0.3 | G27: =Inputs!$C$47 -> 0.0477 | H27: 1
A28: 9 Tax credit 6% | B28: =Inputs!$C$82 -> 0.88 | C28: =Inputs!$C$32 -> 337.83 | D28: =Inputs!$C$25 -> 0.04 | E28: =Inputs!$C$59 -> 10 | F28: =Inputs!$C$89 -> 0.06 | G28: =Inputs!$C$47 -> 0.0477 | H28: 1
A29: 10 Tax credit 0% | B29: =Inputs!$C$82 -> 0.88 | C29: =Inputs!$C$32 -> 337.83 | D29: =Inputs!$C$25 -> 0.04 | E29: =Inputs!$C$59 -> 10 | F29: 0 | G29: =Inputs!$C$47 -> 0.0477 | H29: 1
A30: 11 Treasury base rate +1 point | B30: =Inputs!$C$82 -> 0.88 | C30: =Inputs!$C$32 -> 337.83 | D30: =Inputs!$C$25 -> 0.04 | E30: =Inputs!$C$59 -> 10 | F30: =Inputs!$C$21 -> 0.3 | G30: =Inputs!$C$47+0.01 -> 0.0577 | H30: 1
A31: 12 Treasury base rate −1 point | B31: =Inputs!$C$82 -> 0.88 | C31: =Inputs!$C$32 -> 337.83 | D31: =Inputs!$C$25 -> 0.04 | E31: =Inputs!$C$59 -> 10 | F31: =Inputs!$C$21 -> 0.3 | G31: =Inputs!$C$47-0.01 -> 0.0377 | H31: 1
A32: 13 No overnight recharge | B32: =Inputs!$C$82 -> 0.88 | C32: =Inputs!$C$32 -> 337.83 | D32: =Inputs!$C$25 -> 0.04 | E32: =Inputs!$C$59 -> 10 | F32: =Inputs!$C$21 -> 0.3 | G32: =Inputs!$C$47 -> 0.0477 | H32: 0
A34: Minimum fee and outputs by case | J34: Data Table 1: equity NPV at 12% ($M) by case (rows) and trial fee (columns) | BP34: Data Table 3: case outputs
A35: Case | B35: Minimum fee ($/kW-month) | C35: Change vs base | D35: Fee share of rent | E35: Days covered (of 16) | F35: CAPEX ($M) | G35: PJM charges ($M/yr) | H35: Helper | J35: =Results!$B$23 -> -3.6346341e-06 | K35: 5 | L35: 6 | M35: 7 | N35: 8 | O35: 9 | P35: 10 | Q35: 11 | R35: 12 | S35: 13 | T35: 14 | U35: 15 | V35: 16 | W35: 17 | X35: 18 | Y35: 19 | Z35: 20 | AA35: 21 | AB35: 22 | AC35: 23 | AD35: 24 | AE35: 25 | AF35: 26 | AG35: 27 | AH35: 28 | AI35: 29 | AJ35: 30 | AK35: 31 | AL35: 32 | AM35: 33 | AN35: 34 | AO35: 35 | AP35: 36 | AQ35: 37 | AR35: 38 | AS35: 39 | AT35: 40 | AU35: 41 | AV35: 42 | AW35: 43 | AX35: 44 | AY35: 45 | AZ35: 46 | BA35: 47 | BB35: 48 | BC35: 49 | BD35: 50 | BE35: 51 | BF35: 52 | BG35: 53 | BH35: 54 | BI35: 55 | BJ35: 56 | BK35: 57 | BL35: 58 | BM35: 59 | BN35: 60 | BQ35: =Technical!$B$28 -> 15 | BR35: =Costs!$B$9 -> 135.11553 | BS35: =Costs!$B$20 -> 0.15734271 | BT35: =Technical!$B$40+Technical!$B$41 -> 23.148148
A36: =A20 -> 1 Base case | B36: =INDEX($K$35:$BN$35,$H36)-INDEX($K36:$BN36,$H36)*(INDEX($K$35:$BN$35,$H36+1)-INDEX($K$35:$BN$35,$H36))/(INDEX($K36:$BN36,$H36+1)-INDEX($K36:$BN36,$H36)) -> 27.653367 | C36: =B36-$B$36 -> 0 | D36: =B36*Technical!$B$34*12/10^6/Results!$B$30 -> 0.26616366 | E36: =BQ36 -> 15 | F36: =BR36 -> 135.11553 | G36: =BS36 -> 0.15734271 | H36: =MATCH(0,$K36:$BN36,1) -> 23 | J36: 1 | K36: -106.32289 | L36: -101.53852 | M36: -96.744831 | N36: -91.936016 | O36: -87.142338 | P36: -82.346999 | Q36: -77.533061 | R36: -72.702558 | S36: -67.85724 | T36: -62.998617 | U36: -58.128002 | V36: -53.24654 | W36: -48.355235 | X36: -43.454971 | Y36: -38.546528 | Z36: -33.630601 | AA36: -30.395546 | AB36: -25.775717 | AC36: -21.00755 | AD36: -16.317968 | AE36: -11.824288 | AF36: -7.3570998 | AG36: -2.9028182 | AH36: 1.540042 | AI36: 5.9608631 | AJ36: 10.377744 | AK36: 14.774204 | AL36: 19.163764 | AM36: 23.549643 | AN36: 27.910857 | AO36: 32.269025 | AP36: 36.621107 | AQ36: 40.945401 | AR36: 45.271835 | AS36: 49.600291 | AT36: 53.927992 | AU36: 58.228362 | AV36: 62.530474 | AW36: 66.834238 | AX36: 71.139572 | AY36: 75.446095 | AZ36: 79.723339 | BA36: 84.001953 | BB36: 88.281873 | BC36: 92.563037 | BD36: 96.84539 | BE36: 101.12888 | BF36: 105.40417 | BG36: 109.66006 | BH36: 113.91697 | BI36: 118.17483 | BJ36: 122.43362 | BK36: 126.6933 | BL36: 130.94962 | BM36: 135.18017 | BN36: 139.41152 | BP36: 1 | BQ36: 15 | BR36: 135.11553 | BS36: 0.15734271 | BT36: 23.148148
A37: =A21 -> 2 Installed cost: NREL 2028 low | B37: =INDEX($K$35:$BN$35,$H37)-INDEX($K37:$BN37,$H37)*(INDEX($K$35:$BN$35,$H37+1)-INDEX($K$35:$BN$35,$H37))/(INDEX($K37:$BN37,$H37+1)-INDEX($K37:$BN37,$H37)) -> 20.221836 | C37: =B37-$B$36 -> -7.431531 | D37: =B37*Technical!$B$34*12/10^6/Results!$B$30 -> 0.19463517 | E37: =BQ37 -> 15 | F37: =BR37 -> 105.94286 | G37: =BS37 -> 0.15734271 | H37: =MATCH(0,$K37:$BN37,1) -> 16 | J37: 2 | K37: -70.002793 | L37: -65.260409 | M37: -60.49138 | N37: -55.699121 | O37: -50.886485 | P37: -46.055879 | Q37: -41.209344 | R37: -36.348622 | S37: -31.475211 | T37: -26.590406 | U37: -23.513578 | V37: -18.816275 | W37: -14.163756 | X37: -9.7428063 | Y37: -5.342276 | Z37: -0.96678913 | AA37: 3.3913371 | AB37: 8.4340369 | AC37: 12.802557 | AD37: 17.165756 | AE37: 21.508583 | AF37: 25.844066 | AG37: 30.15422 | AH37: 34.464034 | AI37: 38.777074 | AJ37: 43.066966 | AK37: 47.353827 | AL37: 51.643368 | AM37: 55.935422 | AN37: 60.201455 | AO37: 64.466916 | AP37: 68.734498 | AQ37: 73.004081 | AR37: 77.275552 | AS37: 81.526707 | AT37: 85.771782 | AU37: 90.018479 | AV37: 94.266712 | AW37: 98.515058 | AX37: 102.73758 | AY37: 106.94229 | AZ37: 111.13396 | BA37: 115.32685 | BB37: 119.52092 | BC37: 123.7073 | BD37: 127.88586 | BE37: 132.06544 | BF37: 136.24601 | BG37: 140.42751 | BH37: 144.60992 | BI37: 148.79318 | BJ37: 152.97727 | BK37: 157.16215 | BL37: 161.34778 | BM37: 165.53415 | BN37: 169.71493 | BP37: 2 | BQ37: 15 | BR37: 105.94286 | BS37: 0.15734271 | BT37: 23.148148
A38: =A22 -> 3 Installed cost: NREL 2028 high | B38: =INDEX($K$35:$BN$35,$H38)-INDEX($K38:$BN38,$H38)*(INDEX($K$35:$BN$35,$H38+1)-INDEX($K$35:$BN$35,$H38))/(INDEX($K38:$BN38,$H38+1)-INDEX($K38:$BN38,$H38)) -> 35.615814 | C38: =B38-$B$36 -> 7.962447 | D38: =B38*Technical!$B$34*12/10^6/Results!$B$30 -> 0.34280221 | E38: =BQ38 -> 15 | F38: =BR38 -> 165.8236 | G38: =BS38 -> 0.15734271 | H38: =MATCH(0,$K38:$BN38,1) -> 31 | J38: 3 | K38: -144.6608 | L38: -139.91692 | M38: -135.13605 | N38: -130.32463 | O38: -125.49798 | P38: -120.66506 | Q38: -115.82147 | R38: -110.97007 | S38: -106.15411 | T38: -101.32305 | U38: -96.478181 | V38: -91.620828 | W38: -86.752143 | X38: -81.873146 | Y38: -76.984734 | Z38: -72.087706 | AA38: -67.182771 | AB38: -61.713709 | AC38: -56.735941 | AD38: -51.75158 | AE38: -46.761117 | AF38: -41.764992 | AG38: -37.172699 | AH38: -35.076135 | AI38: -30.295353 | AJ38: -25.511214 | AK38: -20.723934 | AL38: -16.200637 | AM38: -11.69951 | AN38: -7.2156999 | AO38: -2.7447937 | AP38: 1.7123863 | AQ38: 6.1620414 | AR38: 10.591329 | AS38: 15.022833 | AT38: 19.432587 | AU38: 23.834963 | AV38: 28.239246 | AW38: 32.62551 | AX38: 36.999753 | AY38: 41.370866 | AZ38: 45.736617 | BA38: 50.081124 | BB38: 54.417776 | BC38: 58.755819 | BD38: 63.095188 | BE38: 67.435825 | BF38: 71.753679 | BG38: 76.065037 | BH38: 80.377519 | BI38: 84.691077 | BJ38: 89.005666 | BK38: 93.321244 | BL38: 97.623754 | BM38: 101.91033 | BN38: 106.19779 | BP38: 3 | BQ38: 15 | BR38: 165.8236 | BS38: 0.15734271 | BT38: 23.148148
A39: =A23 -> 4 Capacity price: 2029/30 floor | B39: =INDEX($K$35:$BN$35,$H39)-INDEX($K39:$BN39,$H39)*(INDEX($K$35:$BN$35,$H39+1)-INDEX($K$35:$BN$35,$H39))/(INDEX($K39:$BN39,$H39+1)-INDEX($K39:$BN39,$H39)) -> 31.171161 | C39: =B39-$B$36 -> 3.5177938 | D39: =B39*Technical!$B$34*12/10^6/Results!$B$30 -> 0.30002242 | E39: =BQ39 -> 15 | F39: =BR39 -> 135.11553 | G39: =BS39 -> 0.15734271 | H39: =MATCH(0,$K39:$BN39,1) -> 27 | J39: 4 | K39: -124.94587 | L39: -120.16659 | M39: -115.33775 | N39: -110.46848 | O39: -105.57092 | P39: -100.66434 | Q39: -95.750519 | R39: -90.830584 | S39: -85.894733 | T39: -80.943471 | U39: -75.978781 | V39: -71.002323 | W39: -66.01549 | X39: -61.019467 | Y39: -56.015264 | Z39: -51.003747 | AA39: -45.985666 | AB39: -40.96167 | AC39: -35.932327 | AD39: -30.898132 | AE39: -28.693143 | AF39: -23.887338 | AG39: -19.078631 | AH39: -14.314508 | AI39: -9.7794344 | AJ39: -5.2673542 | AK39: -0.76673036 | AL39: 3.7128621 | AM39: 8.1802616 | AN39: 12.631393 | AO39: 17.075204 | AP39: 21.496827 | AQ39: 25.920018 | AR39: 30.32223 | AS39: 34.714964 | AT39: 39.099625 | AU39: 43.468879 | AV39: 47.821874 | AW39: 52.175979 | AX39: 56.531129 | AY39: 62.386583 | AZ39: 66.759825 | BA39: 71.134002 | BB39: 75.509065 | BC39: 79.884968 | BD39: 84.245407 | BE39: 88.591835 | BF39: 92.938991 | BG39: 97.28684 | BH39: 101.63535 | BI39: 105.98449 | BJ39: 110.33422 | BK39: 114.66238 | BL39: 118.98344 | BM39: 123.30503 | BN39: 127.62712 | BP39: 4 | BQ39: 15 | BR39: 135.11553 | BS39: 0.15734271 | BT39: 23.148148
A40: =A24 -> 5 Capacity price: uncollared | B40: =INDEX($K$35:$BN$35,$H40)-INDEX($K40:$BN40,$H40)*(INDEX($K$35:$BN$35,$H40+1)-INDEX($K$35:$BN$35,$H40))/(INDEX($K40:$BN40,$H40+1)-INDEX($K40:$BN40,$H40)) -> 22.873983 | C40: =B40-$B$36 -> -4.7793842 | D40: =B40*Technical!$B$34*12/10^6/Results!$B$30 -> 0.22016208 | E40: =BQ40 -> 15 | F40: =BR40 -> 135.11553 | G40: =BS40 -> 0.15734271 | H40: =MATCH(0,$K40:$BN40,1) -> 18 | J40: 5 | K40: -81.307203 | L40: -76.584717 | M40: -71.842514 | N40: -67.082372 | O40: -62.305859 | P40: -57.514365 | Q40: -52.709129 | R40: -47.891255 | S40: -43.061733 | T40: -38.221452 | U40: -33.37403 | V40: -30.617713 | W40: -26.00269 | X40: -21.327695 | Y40: -16.885749 | Z40: -12.50472 | AA40: -8.1365085 | AB40: -3.7888451 | AC40: 0.54630335 | AD40: 4.8707498 | AE40: 9.1813322 | AF40: 13.480984 | AG40: 17.78076 | AH40: 22.05439 | AI40: 26.325259 | AJ40: 30.591467 | AK40: 34.831405 | AL40: 39.074607 | AM40: 43.320908 | AN40: 47.562943 | AO40: 51.782947 | AP40: 57.298402 | AQ40: 61.567631 | AR40: 65.839423 | AS40: 70.093826 | AT40: 74.338918 | AU40: 78.58627 | AV40: 82.83578 | AW40: 87.087355 | AX40: 91.340904 | AY40: 95.591142 | AZ40: 99.818262 | BA40: 104.04714 | BB40: 108.27772 | BC40: 112.50991 | BD40: 116.74366 | BE40: 120.9726 | BF40: 125.17811 | BG40: 129.35685 | BH40: 133.53378 | BI40: 137.71203 | BJ40: 141.89156 | BK40: 146.07232 | BL40: 150.25029 | BM40: 154.41556 | BN40: 158.58195 | BP40: 5 | BQ40: 15 | BR40: 135.11553 | BS40: 0.15734271 | BT40: 23.148148
A41: =A25 -> 6 Fixed O&M: NREL literal | B41: =INDEX($K$35:$BN$35,$H41)-INDEX($K41:$BN41,$H41)*(INDEX($K$35:$BN$35,$H41+1)-INDEX($K$35:$BN$35,$H41))/(INDEX($K41:$BN41,$H41+1)-INDEX($K41:$BN41,$H41)) -> 22.074055 | C41: =B41-$B$36 -> -5.5793115 | D41: =B41*Technical!$B$34*12/10^6/Results!$B$30 -> 0.21246278 | E41: =BQ41 -> 15 | F41: =BR41 -> 135.11553 | G41: =BS41 -> 0.15734271 | H41: =MATCH(0,$K41:$BN41,1) -> 18 | J41: 6 | K41: -79.385401 | L41: -74.593815 | M41: -69.779974 | N41: -64.946731 | O41: -60.096469 | P41: -55.231197 | Q41: -50.352621 | R41: -45.462196 | S41: -40.561173 | T41: -35.650634 | U41: -31.41398 | V41: -28.428427 | W41: -23.707847 | X41: -18.98222 | Y41: -14.45196 | Z41: -10.007188 | AA41: -5.5794925 | AB41: -0.3295044 | AC41: 4.1199208 | AD41: 8.5411424 | AE41: 12.964873 | AF41: 17.365687 | AG41: 21.762263 | AH41: 26.156516 | AI41: 30.524827 | AJ41: 34.893032 | AK41: 39.254365 | AL41: 43.588593 | AM41: 47.922045 | AN41: 52.25744 | AO41: 56.594662 | AP41: 60.90834 | AQ41: 65.217221 | AR41: 69.527655 | AS41: 73.839557 | AT41: 78.152848 | AU41: 82.44929 | AV41: 86.734257 | AW41: 91.020424 | AX41: 95.30773 | AY41: 99.596119 | AZ41: 103.88554 | BA41: 108.17594 | BB41: 112.44504 | BC41: 116.70765 | BD41: 120.97113 | BE41: 125.23543 | BF41: 129.50051 | BG41: 133.76635 | BH41: 138.01938 | BI41: 142.25594 | BJ41: 146.49316 | BK41: 150.70844 | BL41: 154.91613 | BM41: 159.12443 | BN41: 163.3333 | BP41: 6 | BQ41: 15 | BR41: 135.11553 | BS41: 0.15734271 | BT41: 23.148148
A42: =A26 -> 7 Duration 5 h | B42: =INDEX($K$35:$BN$35,$H42)-INDEX($K42:$BN42,$H42)*(INDEX($K$35:$BN$35,$H42+1)-INDEX($K$35:$BN$35,$H42))/(INDEX($K42:$BN42,$H42+1)-INDEX($K42:$BN42,$H42)) -> 12.905836 | C42: =B42-$B$36 -> -14.747531 | D42: =B42*Technical!$B$34*12/10^6/Results!$B$30 -> 0.12421867 | E42: =BQ42 -> 5 | F42: =BR42 -> 76.591369 | G42: =BS42 -> 0.38051448 | H42: =MATCH(0,$K42:$BN42,1) -> 8 | J42: 7 | K42: -35.448821 | L42: -30.661477 | M42: -25.8515 | N42: -21.02179 | O42: -17.368093 | P42: -12.719163 | Q42: -8.279017 | R42: -3.9229677 | S42: 0.40780351 | T42: 4.7176981 | U42: 9.0109864 | V42: 13.279815 | W42: 17.534823 | X42: 21.769625 | Y42: 26.00926 | Z42: 30.222918 | AA42: 34.441471 | AB42: 39.448814 | AC42: 43.68851 | AD42: 47.932281 | AE42: 52.179825 | AF42: 56.406512 | AG42: 60.630633 | AH42: 64.857827 | AI42: 69.074029 | AJ42: 73.250467 | AK42: 77.423099 | AL42: 81.598155 | AM42: 85.766775 | AN42: 89.928396 | AO42: 94.092042 | AP42: 98.257597 | AQ42: 102.42495 | AR42: 106.594 | AS42: 110.76466 | AT42: 114.93683 | AU42: 119.1021 | AV42: 123.2635 | AW42: 127.42619 | AX42: 131.59013 | AY42: 135.75523 | AZ42: 139.92145 | BA42: 144.08873 | BB42: 148.25703 | BC42: 152.42629 | BD42: 156.59647 | BE42: 160.76193 | BF42: 164.92552 | BG42: 169.08992 | BH42: 173.2551 | BI42: 177.42101 | BJ42: 181.58763 | BK42: 185.75493 | BL42: 189.92289 | BM42: 194.09146 | BN42: 198.26064 | BP42: 7 | BQ42: 5 | BR42: 76.591369 | BS42: 0.38051448 | BT42: 151.3203
A43: =A27 -> 8 Duration 15 h | B43: =INDEX($K$35:$BN$35,$H43)-INDEX($K43:$BN43,$H43)*(INDEX($K$35:$BN$35,$H43+1)-INDEX($K$35:$BN$35,$H43))/(INDEX($K43:$BN43,$H43+1)-INDEX($K43:$BN43,$H43)) -> 42.713085 | C43: =B43-$B$36 -> 15.059719 | D43: =B43*Technical!$B$34*12/10^6/Results!$B$30 -> 0.41111345 | E43: =BQ43 -> 16 | F43: =BR43 -> 193.63969 | G43: =BS43 -> 0.090204689 | H43: =MATCH(0,$K43:$BN43,1) -> 38 | J43: 8 | K43: -178.84923 | L43: -174.15296 | M43: -169.41545 | N43: -164.64199 | O43: -159.83699 | P43: -155.00419 | Q43: -150.15435 | R43: -145.29702 | S43: -140.43436 | T43: -135.56263 | U43: -130.6859 | V43: -125.84191 | W43: -120.99302 | X43: -116.13263 | Y43: -111.26174 | Z43: -106.38125 | AA43: -101.49194 | AB43: -96.213107 | AC43: -91.250261 | AD43: -86.280066 | AE43: -81.303066 | AF43: -76.319755 | AG43: -71.330579 | AH43: -66.335943 | AI43: -61.336217 | AJ43: -56.331736 | AK43: -51.322808 | AL43: -46.309714 | AM43: -42.699508 | AN43: -40.259552 | AO43: -35.46832 | AP43: -30.674528 | AQ43: -25.878325 | AR43: -21.192063 | AS43: -16.671578 | AT43: -12.164644 | AU43: -7.6707367 | AV43: -3.1846912 | AW43: 1.2813809 | AX43: 5.7493167 | AY43: 10.195195 | AZ43: 14.634055 | BA43: 19.074539 | BB43: 23.49413 | BC43: 27.904543 | BD43: 32.316384 | BE43: 36.729589 | BF43: 41.110843 | BG43: 45.493148 | BH43: 49.872077 | BI43: 54.245066 | BJ43: 58.605548 | BK43: 62.948773 | BL43: 67.293038 | BM43: 71.638303 | BN43: 75.984527 | BP43: 8 | BQ43: 16 | BR43: 193.63969 | BS43: 0.090204689 | BT43: 0
A44: =A28 -> 9 Tax credit 6% | B44: =INDEX($K$35:$BN$35,$H44)-INDEX($K44:$BN44,$H44)*(INDEX($K$35:$BN$35,$H44+1)-INDEX($K$35:$BN$35,$H44))/(INDEX($K44:$BN44,$H44+1)-INDEX($K44:$BN44,$H44)) -> 33.299969 | C44: =B44-$B$36 -> 5.6466024 | D44: =B44*Technical!$B$34*12/10^6/Results!$B$30 -> 0.32051221 | E44: =BQ44 -> 15 | F44: =BR44 -> 135.11553 | G44: =BS44 -> 0.15734271 | H44: =MATCH(0,$K44:$BN44,1) -> 29 | J44: 9 | K44: -132.38088 | L44: -127.59652 | M44: -122.80283 | N44: -117.99401 | O44: -113.20033 | P44: -108.40499 | Q44: -103.59106 | R44: -98.760553 | S44: -93.915234 | T44: -89.056611 | U44: -84.185996 | V44: -79.304534 | W44: -74.41323 | X44: -69.512966 | Y44: -64.604523 | Z44: -59.688596 | AA44: -54.765799 | AB44: -49.079299 | AC44: -45.71594 | AD44: -42.268511 | AE44: -37.491661 | AF44: -32.71094 | AG44: -28.102862 | AH44: -23.600427 | AI44: -19.121969 | AJ44: -14.652064 | AK44: -10.19927 | AL44: -5.7540506 | AM44: -1.32835 | AN44: 3.0999358 | AO44: 7.5008375 | AP44: 11.900599 | AQ44: 16.30255 | AR44: 20.673957 | AS44: 25.046331 | AT44: 29.409951 | AU44: 33.763172 | AV44: 38.097067 | AW44: 42.43259 | AX44: 46.769659 | AY44: 51.108197 | AZ44: 55.425168 | BA44: 59.734761 | BB44: 64.045639 | BC44: 68.357744 | BD44: 72.671018 | BE44: 76.98541 | BF44: 81.274595 | BG44: 85.560201 | BH44: 89.846798 | BI44: 94.134344 | BJ44: 98.422799 | BK44: 102.71213 | BL44: 107.00229 | BM44: 111.2898 | BN44: 115.55191 | BP44: 9 | BQ44: 15 | BR44: 135.11553 | BS44: 0.15734271 | BT44: 23.148148
A45: =A29 -> 10 Tax credit 0% | B45: =INDEX($K$35:$BN$35,$H45)-INDEX($K45:$BN45,$H45)*(INDEX($K$35:$BN$35,$H45+1)-INDEX($K$35:$BN$35,$H45))/(INDEX($K45:$BN45,$H45+1)-INDEX($K45:$BN45,$H45)) -> 34.709536 | C45: =B45-$B$36 -> 7.056169 | D45: =B45*Technical!$B$34*12/10^6/Results!$B$30 -> 0.33407928 | E45: =BQ45 -> 15 | F45: =BR45 -> 135.11553 | G45: =BS45 -> 0.15734271 | H45: =MATCH(0,$K45:$BN45,1) -> 30 | J45: 10 | K45: -138.89538 | L45: -134.11101 | M45: -129.31732 | N45: -124.50851 | O45: -119.71483 | P45: -114.91949 | Q45: -110.10555 | R45: -105.27505 | S45: -100.42973 | T45: -95.57111 | U45: -90.700495 | V45: -85.819033 | W45: -80.927728 | X45: -76.027464 | Y45: -71.119022 | Z45: -66.203094 | AA45: -61.280298 | AB45: -55.593797 | AC45: -50.598973 | AD45: -48.77692 | AE45: -44.00007 | AF45: -39.219349 | AG45: -34.435031 | AH45: -29.916711 | AI45: -25.419345 | AJ45: -20.937623 | AK45: -16.471322 | AL45: -12.015632 | AM45: -7.5720393 | AN45: -3.1437535 | AO45: 1.2869638 | AP45: 5.6886763 | AQ45: 10.090627 | AR45: 14.494644 | AS45: 18.869987 | AT45: 23.244235 | AU45: 27.611334 | AV45: 31.972151 | AW45: 36.307674 | AX45: 40.644742 | AY45: 44.98328 | AZ45: 49.323215 | BA45: 53.652393 | BB45: 57.963272 | BC45: 62.275376 | BD45: 66.588651 | BE45: 70.903043 | BF45: 75.218502 | BG45: 79.525488 | BH45: 83.812085 | BI45: 88.099631 | BJ45: 92.388086 | BK45: 96.677412 | BL45: 100.96757 | BM45: 105.25854 | BN45: 109.55027 | BP45: 10 | BQ45: 15 | BR45: 135.11553 | BS45: 0.15734271 | BT45: 23.148148
A46: =A30 -> 11 Treasury base rate +1 point | B46: =INDEX($K$35:$BN$35,$H46)-INDEX($K46:$BN46,$H46)*(INDEX($K$35:$BN$35,$H46+1)-INDEX($K$35:$BN$35,$H46))/(INDEX($K46:$BN46,$H46+1)-INDEX($K46:$BN46,$H46)) -> 28.390007 | C46: =B46-$B$36 -> 0.73664005 | D46: =B46*Technical!$B$34*12/10^6/Results!$B$30 -> 0.27325382 | E46: =BQ46 -> 15 | F46: =BR46 -> 135.11553 | G46: =BS46 -> 0.15734271 | H46: =MATCH(0,$K46:$BN46,1) -> 24 | J46: 11 | K46: -105.68855 | L46: -101.08312 | M46: -96.474551 | N46: -91.856975 | O46: -87.254169 | P46: -82.65068 | Q46: -78.033095 | R46: -73.402957 | S46: -68.761592 | T46: -64.110144 | U46: -59.449608 | V46: -54.780853 | W46: -50.104637 | X46: -45.421633 | Y46: -40.73243 | Z46: -36.037556 | AA46: -32.61529 | AB46: -28.059302 | AC46: -23.471695 | AD46: -18.880623 | AE46: -14.533078 | AF46: -10.227126 | AG46: -5.9315339 | AH46: -1.6636215 | AI46: 2.6019977 | AJ46: 6.8432888 | AK46: 11.087118 | AL46: 15.302049 | AM46: 19.518308 | AN46: 23.725928 | AO46: 27.913845 | AP46: 32.098414 | AQ46: 36.277081 | AR46: 40.428201 | AS46: 44.580986 | AT46: 48.735347 | AU46: 52.891199 | AV46: 57.021893 | AW46: 61.150005 | AX46: 65.279416 | AY46: 69.410061 | AZ46: 73.541878 | BA46: 77.658724 | BB46: 81.763043 | BC46: 85.868396 | BD46: 89.974737 | BE46: 94.08202 | BF46: 98.190204 | BG46: 102.29925 | BH46: 106.39471 | BI46: 110.47695 | BJ46: 114.55997 | BK46: 118.64372 | BL46: 122.72818 | BM46: 126.81332 | BN46: 130.89692 | BP46: 11 | BQ46: 15 | BR46: 135.11553 | BS46: 0.15734271 | BT46: 23.148148
A47: =A31 -> 12 Treasury base rate −1 point | B47: =INDEX($K$35:$BN$35,$H47)-INDEX($K47:$BN47,$H47)*(INDEX($K$35:$BN$35,$H47+1)-INDEX($K$35:$BN$35,$H47))/(INDEX($K47:$BN47,$H47+1)-INDEX($K47:$BN47,$H47)) -> 26.906285 | C47: =B47-$B$36 -> -0.74708211 | D47: =B47*Technical!$B$34*12/10^6/Results!$B$30 -> 0.25897299 | E47: =BQ47 -> 15 | F47: =BR47 -> 135.11553 | G47: =BS47 -> 0.15734271 | H47: =MATCH(0,$K47:$BN47,1) -> 22 | J47: 12 | K47: -107.02224 | L47: -102.04017 | M47: -97.04252 | N47: -92.023078 | O47: -87.019154 | P47: -82.012491 | Q47: -76.982266 | R47: -71.931058 | S47: -66.861082 | T47: -61.774252 | U47: -56.672231 | V47: -51.55647 | W47: -46.428241 | X47: -41.288662 | Y47: -36.138723 | Z47: -30.979788 | AA47: -27.950494 | AB47: -23.258964 | AC47: -18.291799 | AD47: -13.525182 | AE47: -8.8543715 | AF47: -4.19744 | AG47: 0.43403967 | AH47: 5.0554491 | AI47: 9.6617519 | AJ47: 14.255955 | AK47: 18.835367 | AL47: 23.415486 | AM47: 27.96667 | AN47: 32.514788 | AO47: 37.055886 | AP47: 41.570148 | AQ47: 46.087119 | AR47: 50.606644 | AS47: 55.117278 | AT47: 59.608247 | AU47: 64.101403 | AV47: 68.596633 | AW47: 73.093828 | AX47: 77.575659 | AY47: 82.044034 | AZ47: 86.514117 | BA47: 90.985825 | BB47: 95.459081 | BC47: 99.933812 | BD47: 104.4042 | BE47: 108.85051 | BF47: 113.29812 | BG47: 117.74697 | BH47: 122.19701 | BI47: 126.64819 | BJ47: 131.08921 | BK47: 135.51018 | BL47: 139.9194 | BM47: 144.30977 | BN47: 148.70108 | BP47: 12 | BQ47: 15 | BR47: 135.11553 | BS47: 0.15734271 | BT47: 23.148148
A48: =A32 -> 13 No overnight recharge | B48: =INDEX($K$35:$BN$35,$H48)-INDEX($K48:$BN48,$H48)*(INDEX($K$35:$BN$35,$H48+1)-INDEX($K$35:$BN$35,$H48))/(INDEX($K48:$BN48,$H48+1)-INDEX($K48:$BN48,$H48)) -> 28.006669 | C48: =B48-$B$36 -> 0.35330191 | D48: =B48*Technical!$B$34*12/10^6/Results!$B$30 -> 0.26956419 | E48: =BQ48 -> 10 | F48: =BR48 -> 135.11553 | G48: =BS48 -> 0.37367635 | H48: =MATCH(0,$K48:$BN48,1) -> 24 | J48: 13 | K48: -108.05485 | L48: -103.26839 | M48: -98.471864 | N48: -93.663172 | O48: -88.854322 | P48: -84.062674 | Q48: -79.252146 | R48: -74.424805 | S48: -69.582425 | T48: -64.726542 | U48: -59.858486 | V48: -54.97942 | W48: -50.090364 | X48: -45.192213 | Y48: -40.285762 | Z48: -35.371713 | AA48: -31.038611 | AB48: -27.464379 | AC48: -22.697546 | AD48: -17.926138 | AE48: -13.412964 | AF48: -8.9360857 | AG48: -4.4712349 | AH48: -0.029555056 | AI48: 4.4022167 | AJ48: 8.8180062 | AK48: 13.225728 | AL48: 17.614273 | AM48: 22.005651 | AN48: 26.371909 | AO48: 30.733532 | AP48: 35.086936 | AQ48: 39.420082 | AR48: 43.74569 | AS48: 48.07335 | AT48: 52.402951 | AU48: 56.711675 | AV48: 61.013062 | AW48: 65.316126 | AX48: 69.620783 | AY48: 73.926953 | AZ48: 78.214734 | BA48: 82.492726 | BB48: 86.772044 | BC48: 91.052625 | BD48: 95.334412 | BE48: 99.617349 | BF48: 103.90139 | BG48: 108.15848 | BH48: 112.41488 | BI48: 116.67225 | BJ48: 120.93056 | BK48: 125.18976 | BL48: 129.44859 | BM48: 133.68714 | BN48: 137.91804 | BP48: 13 | BQ48: 10 | BR48: 135.11553 | BS48: 0.37367635 | BT48: 150.46296
A50: Tornado summary
A51: Input and range | B51: Fee, low input | C51: Fee, high input | D51: Difference
A52: Installed cost: NREL 2028 low / high (0.69 / 1.08) | B52: =B37 -> 20.221836 | C52: =B38 -> 35.615814 | D52: =ABS(C52-B52) -> 15.393978
A53: Capacity price: $181.91 floor / $554.72 uncollared | B53: =B39 -> 31.171161 | C53: =B40 -> 22.873983 | D53: =ABS(C53-B53) -> 8.297178
A54: Fixed O&M: NREL literal 1.92% / base 4% | B54: =B41 -> 22.074055 | C54: =B36 -> 27.653367 | D54: =ABS(C54-B54) -> 5.5793115
A56: Thresholds
A57: Minimum fee for a 12% equity return (base case) | B57: =B36 -> 27.653367
A58: Fee change per 10% of base CAPEX | B58: =(B38-B37)/((Inputs!$C$88-Inputs!$C$87)/Inputs!$C$82)*0.1 -> 3.473513
A59: Base CAPEX ($M) | B59: =Costs!$B$9 -> 135.11553
A61: Maximum CAPEX for a customer fee ceiling | J61: Data Table 2: equity NPV at 12% ($M) by fee ceiling (rows) and NREL cost factor (columns)
A62: Customer's maximum fee ($/kW-month) | B62: Basis | C62: Maximum NREL cost factor | D62: CAPEX change vs base | E62: Maximum CAPEX ($M) | H62: Helper | J62: =Results!$B$23 -> -3.6346341e-06 | K62: 0.2 | L62: 0.21 | M62: 0.22 | N62: 0.23 | O62: 0.24 | P62: 0.25 | Q62: 0.26 | R62: 0.27 | S62: 0.28 | T62: 0.29 | U62: 0.3 | V62: 0.31 | W62: 0.32 | X62: 0.33 | Y62: 0.34 | Z62: 0.35 | AA62: 0.36 | AB62: 0.37 | AC62: 0.38 | AD62: 0.39 | AE62: 0.4 | AF62: 0.41 | AG62: 0.42 | AH62: 0.43 | AI62: 0.44 | AJ62: 0.45 | AK62: 0.46 | AL62: 0.47 | AM62: 0.48 | AN62: 0.49 | AO62: 0.5 | AP62: 0.51 | AQ62: 0.52 | AR62: 0.53 | AS62: 0.54 | AT62: 0.55 | AU62: 0.56 | AV62: 0.57 | AW62: 0.58 | AX62: 0.59 | AY62: 0.6 | AZ62: 0.61 | BA62: 0.62 | BB62: 0.63 | BC62: 0.64 | BD62: 0.65 | BE62: 0.66 | BF62: 0.67 | BG62: 0.68 | BH62: 0.69 | BI62: 0.7 | BJ62: 0.71 | BK62: 0.72 | BL62: 0.73 | BM62: 0.74 | BN62: 0.75 | BO62: 0.76 | BP62: 0.77 | BQ62: 0.78 | BR62: 0.79 | BS62: 0.8 | BT62: 0.81 | BU62: 0.82 | BV62: 0.83 | BW62: 0.84 | BX62: 0.85 | BY62: 0.86 | BZ62: 0.87 | CA62: 0.88 | CB62: 0.89 | CC62: 0.9 | CD62: 0.91 | CE62: 0.92 | CF62: 0.93 | CG62: 0.94 | CH62: 0.95 | CI62: 0.96 | CJ62: 0.97 | CK62: 0.98 | CL62: 0.99 | CM62: 1 | CN62: 1.01 | CO62: 1.02 | CP62: 1.03 | CQ62: 1.04 | CR62: 1.05 | CS62: 1.06 | CT62: 1.07 | CU62: 1.08 | CV62: 1.09 | CW62: 1.1 | CX62: 1.11 | CY62: 1.12 | CZ62: 1.13 | DA62: 1.14 | DB62: 1.15 | DC62: 1.16 | DD62: 1.17 | DE62: 1.18 | DF62: 1.19 | DG62: 1.2 | DH62: 1.21 | DI62: 1.22 | DJ62: 1.23 | DK62: 1.24 | DL62: 1.25 | DM62: 1.26 | DN62: 1.27 | DO62: 1.28 | DP62: 1.29 | DQ62: 1.3
A63: 35 | B63: Round-number test | C63: =INDEX($K$62:$DQ$62,$H63)+INDEX($K63:$DQ63,$H63)*(INDEX($K$62:$DQ$62,$H63+1)-INDEX($K$62:$DQ$62,$H63))/(INDEX($K63:$DQ63,$H63)-INDEX($K63:$DQ63,$H63+1)) -> 1.0645242 | D63: =C63/Inputs!$C$82-1 -> 0.20968662 | E63: =(Technical!$B$33*Inputs!$C$19+Technical!$B$32*Inputs!$C$20)/10^6*Costs!$B$8*C63 -> 163.44745 | H63: =MATCH(0,$K63:$DQ63,-1) -> 87 | J63: =A63 -> 35 | K63: 142.35395 | L63: 140.79577 | M63: 139.23759 | N63: 137.6794 | O63: 136.12122 | P63: 134.56304 | Q63: 133.00486 | R63: 131.44667 | S63: 129.88849 | T63: 128.33031 | U63: 126.77213 | V63: 125.21394 | W63: 123.65576 | X63: 122.09758 | Y63: 120.53939 | Z63: 118.98121 | AA63: 117.42303 | AB63: 115.86485 | AC63: 114.30355 | AD63: 112.73514 | AE63: 111.16673 | AF63: 109.59832 | AG63: 108.02991 | AH63: 106.4615 | AI63: 104.89309 | AJ63: 103.32435 | AK63: 101.74207 | AL63: 100.1598 | AM63: 98.577521 | AN63: 96.995245 | AO63: 95.412969 | AP63: 93.830693 | AQ63: 92.248417 | AR63: 90.66614 | AS63: 89.072373 | AT63: 87.47485 | AU63: 85.877327 | AV63: 84.279803 | AW63: 82.668382 | AX63: 81.037476 | AY63: 79.390256 | AZ63: 77.742956 | BA63: 76.095655 | BB63: 74.448354 | BC63: 72.801054 | BD63: 71.14059 | BE63: 69.472172 | BF63: 67.803753 | BG63: 66.135335 | BH63: 64.466916 | BI63: 62.798497 | BJ63: 61.130079 | BK63: 59.46166 | BL63: 57.77477 | BM63: 56.086845 | BN63: 54.39892 | BO63: 52.710995 | BP63: 51.02307 | BQ63: 49.335145 | BR63: 47.64722 | BS63: 45.946751 | BT63: 44.240792 | BU63: 42.534833 | BV63: 40.828874 | BW63: 39.122915 | BX63: 37.416956 | BY63: 35.710997 | BZ63: 33.991671 | CA63: 32.269025 | CB63: 30.545998 | CC63: 28.817423 | CD63: 27.088847 | CE63: 25.360272 | CF63: 23.62472 | CG63: 21.879959 | CH63: 20.135197 | CI63: 18.390435 | CJ63: 16.645674 | CK63: 14.900912 | CL63: 13.148287 | CM63: 11.388549 | CN63: 9.6288102 | CO63: 7.8690717 | CP63: 6.1093332 | CQ63: 4.3495948 | CR63: 2.5760278 | CS63: 0.80242067 | CT63: -0.97118651 | CU63: -2.7447937 | CV63: -4.5184009 | CW63: -6.3020814 | CX63: -8.088541 | CY63: -9.8750007 | CZ63: -11.66146 | DA63: -13.44792 | DB63: -15.244806 | DC63: -17.043185 | DD63: -18.841564 | DE63: -20.639944 | DF63: -22.465047 | DG63: -24.366674 | DH63: -26.268301 | DI63: -28.169927 | DJ63: -30.071554 | DK63: -31.973181 | DL63: -33.874808 | DM63: -35.776435 | DN63: -37.678062 | DO63: -39.579689 | DP63: -41.481316 | DQ63: -42.971359
A64: 30 | B64: Round-number test | C64: =INDEX($K$62:$DQ$62,$H64)+INDEX($K64:$DQ64,$H64)*(INDEX($K$62:$DQ$62,$H64+1)-INDEX($K$62:$DQ$62,$H64))/(INDEX($K64:$DQ64,$H64)-INDEX($K64:$DQ64,$H64+1)) -> 0.93892067 | D64: =C64/Inputs!$C$82-1 -> 0.066955311 | E64: =(Technical!$B$33*Inputs!$C$19+Technical!$B$32*Inputs!$C$20)/10^6*Costs!$B$8*C64 -> 144.16223 | H64: =MATCH(0,$K64:$DQ64,-1) -> 74 | J64: =A64 -> 30 | K64: 121.57832 | L64: 120.02294 | M64: 118.46756 | N64: 116.91218 | O64: 115.3568 | P64: 113.80142 | Q64: 112.24604 | R64: 110.69066 | S64: 109.13528 | T64: 107.5799 | U64: 106.02452 | V64: 104.46914 | W64: 102.91376 | X64: 101.35838 | Y64: 99.79892 | Z64: 98.2333 | AA64: 96.667679 | AB64: 95.102059 | AC64: 93.536439 | AD64: 91.970818 | AE64: 90.405198 | AF64: 88.826513 | AG64: 87.247009 | AH64: 85.667504 | AI64: 84.087999 | AJ64: 82.508495 | AK64: 80.92899 | AL64: 79.349485 | AM64: 77.760746 | AN64: 76.16597 | AO64: 74.571194 | AP64: 72.976418 | AQ64: 71.364685 | AR64: 69.725963 | AS64: 68.081319 | AT64: 66.436676 | AU64: 64.792033 | AV64: 63.147389 | AW64: 61.487438 | AX64: 59.821638 | AY64: 58.155838 | AZ64: 56.490037 | BA64: 54.824237 | BB64: 53.158437 | BC64: 51.492637 | BD64: 49.808348 | BE64: 48.123002 | BF64: 46.437657 | BG64: 44.752311 | BH64: 43.066966 | BI64: 41.38162 | BJ64: 39.686291 | BK64: 37.982873 | BL64: 36.279456 | BM64: 34.576038 | BN64: 32.872621 | BO64: 31.169203 | BP64: 29.457843 | BQ64: 27.737701 | BR64: 26.017324 | BS64: 24.291351 | BT64: 22.565266 | BU64: 20.839181 | BV64: 19.099158 | BW64: 17.356851 | BX64: 15.614543 | BY64: 13.872235 | BZ64: 12.129927 | CA64: 10.377744 | CB64: 8.6204257 | CC64: 6.8631068 | CD64: 5.105788 | CE64: 3.3484692 | CF64: 1.580047 | CG64: -0.19117244 | CH64: -1.9623919 | CI64: -3.7336113 | CJ64: -5.507654 | CK64: -7.2917552 | CL64: -9.0758565 | CM64: -10.859958 | CN64: -12.644059 | CO64: -14.439026 | CP64: -16.235073 | CQ64: -18.031121 | CR64: -19.827168 | CS64: -21.712174 | CT64: -23.611694 | CU64: -25.511214 | CV64: -27.410733 | CW64: -29.310253 | CX64: -31.209773 | CY64: -33.109292 | CZ64: -35.008812 | DA64: -36.908332 | DB64: -38.275131 | DC64: -39.123875 | DD64: -39.972618 | DE64: -41.135273 | DF64: -43.075664 | DG64: -45.016056 | DH64: -46.956447 | DI64: -48.896838 | DJ64: -50.837229 | DK64: -52.77762 | DL64: -54.718012 | DM64: -56.658403 | DN64: -58.598794 | DO64: -60.539185 | DP64: -62.479576 | DQ64: -64.419968
A65: 25 | B65: Round-number test | C65: =INDEX($K$62:$DQ$62,$H65)+INDEX($K65:$DQ65,$H65)*(INDEX($K$62:$DQ$62,$H65+1)-INDEX($K$62:$DQ$62,$H65))/(INDEX($K65:$DQ65,$H65)-INDEX($K65:$DQ65,$H65+1)) -> 0.8133978 | D65: =C65/Inputs!$C$82-1 -> -0.075684313 | E65: =(Technical!$B$33*Inputs!$C$19+Technical!$B$32*Inputs!$C$20)/10^6*Costs!$B$8*C65 -> 124.8894 | H65: =MATCH(0,$K65:$DQ65,-1) -> 62 | J65: =A65 -> 25 | K65: 100.8473 | L65: 99.295418 | M65: 97.743534 | N65: 96.19165 | O65: 94.639767 | P65: 93.087883 | Q65: 91.535999 | R65: 89.984116 | S65: 88.432232 | T65: 86.880348 | U65: 85.323295 | V65: 83.761156 | W65: 82.199017 | X65: 80.636878 | Y65: 79.074739 | Z65: 77.512599 | AA65: 75.938333 | AB65: 74.362286 | AC65: 72.786238 | AD65: 71.210191 | AE65: 69.634144 | AF65: 68.058096 | AG65: 66.474845 | AH65: 64.883496 | AI65: 63.292148 | AJ65: 61.700799 | AK65: 60.083867 | AL65: 58.442538 | AM65: 56.80121 | AN65: 55.159881 | AO65: 53.518553 | AP65: 51.859398 | AQ65: 50.196864 | AR65: 48.53433 | AS65: 46.871796 | AT65: 45.209262 | AU65: 43.546728 | AV65: 41.865335 | AW65: 40.183208 | AX65: 38.50108 | AY65: 36.818952 | AZ65: 35.136824 | BA65: 33.446956 | BB65: 31.746709 | BC65: 30.046462 | BD65: 28.346214 | BE65: 26.645967 | BF65: 24.942924 | BG65: 23.225907 | BH65: 21.508583 | BI65: 19.785932 | BJ65: 18.062954 | BK65: 16.335013 | BL65: 14.595767 | BM65: 12.85652 | BN65: 11.117274 | BO65: 9.378027 | BP65: 7.6266175 | BQ65: 5.872317 | BR65: 4.1180165 | BS65: 2.363716 | BT65: 0.60081371 | BU65: -1.1674271 | BV65: -2.935668 | BW65: -4.7039089 | BX65: -6.48081 | BY65: -8.2619692 | BZ65: -10.043128 | CA65: -11.824288 | CB65: -13.616939 | CC65: -15.410077 | CD65: -17.203216 | CE65: -19.045588 | CF65: -20.94248 | CG65: -22.839371 | CH65: -24.736262 | CI65: -26.633153 | CJ65: -28.530044 | CK65: -30.426935 | CL65: -32.323826 | CM65: -33.573377 | CN65: -34.439914 | CO65: -35.306451 | CP65: -37.075856 | CQ65: -39.012908 | CR65: -40.94996 | CS65: -42.887012 | CT65: -44.824064 | CU65: -46.761117 | CV65: -48.698169 | CW65: -50.635221 | CX65: -52.572273 | CY65: -54.509325 | CZ65: -56.446377 | DA65: -58.383429 | DB65: -60.320481 | DC65: -62.257533 | DD65: -64.194586 | DE65: -66.131638 | DF65: -68.06869 | DG65: -70.005742 | DH65: -71.942794 | DI65: -73.879846 | DJ65: -75.816898 | DK65: -77.75395 | DL65: -79.691003 | DM65: -81.628055 | DN65: -83.565107 | DO65: -85.502159 | DP65: -87.439211 | DQ65: -89.376263
A66: =Customer!$B$11 -> 15.58477 | B66: RBP route, auction price $0 | C66: =INDEX($K$62:$DQ$62,$H66)+INDEX($K66:$DQ66,$H66)*(INDEX($K$62:$DQ$62,$H66+1)-INDEX($K$62:$DQ$62,$H66))/(INDEX($K66:$DQ66,$H66)-INDEX($K66:$DQ66,$H66+1)) -> 0.57450591 | D66: =C66/Inputs!$C$82-1 -> -0.34715238 | E66: =(Technical!$B$33*Inputs!$C$19+Technical!$B$32*Inputs!$C$20)/10^6*Costs!$B$8*C66 -> 88.209852 | H66: =MATCH(0,$K66:$DQ66,-1) -> 38 | J66: =A66 -> 15.58477 | K66: 61.29639 | L66: 59.760736 | M66: 58.220569 | N66: 56.674632 | O66: 55.128696 | P66: 53.582759 | Q66: 52.031408 | R66: 50.471521 | S66: 48.911634 | T66: 47.351748 | U66: 45.791861 | V66: 44.22009 | W66: 42.644849 | X66: 41.069608 | Y66: 39.46241 | Z66: 37.836987 | AA66: 36.211564 | AB66: 34.574906 | AC66: 32.928193 | AD66: 31.28148 | AE66: 29.634767 | AF66: 27.981046 | AG66: 26.314656 | AH66: 24.648265 | AI66: 22.981875 | AJ66: 21.307399 | AK66: 19.622807 | AL66: 17.938216 | AM66: 16.253625 | AN66: 14.556825 | AO66: 12.854552 | AP66: 11.14731 | AQ66: 9.4352745 | AR66: 7.7115001 | AS66: 5.9877257 | AT66: 4.2623625 | AU66: 2.5234628 | AV66: 0.78456319 | AW66: -0.95662443 | AX66: -2.7095301 | AY66: -4.4624358 | AZ66: -6.22049 | BA66: -7.986374 | BB66: -9.7522581 | BC66: -11.527748 | BD66: -13.305666 | BE66: -15.121199 | BF66: -17.003326 | BG66: -18.885452 | BH66: -20.767579 | BI66: -22.649705 | BJ66: -24.438109 | BK66: -25.404589 | BL66: -26.502084 | BM66: -28.419592 | BN66: -30.337816 | BO66: -32.256039 | BP66: -34.174262 | BQ66: -36.092486 | BR66: -38.010709 | BS66: -39.928932 | BT66: -41.847156 | BU66: -43.765379 | BV66: -45.683602 | BW66: -47.601825 | BX66: -49.520049 | BY66: -51.438272 | BZ66: -53.356495 | CA66: -55.274719 | CB66: -57.192942 | CC66: -59.111165 | CD66: -61.029389 | CE66: -62.947612 | CF66: -64.865835 | CG66: -66.784059 | CH66: -68.702282 | CI66: -70.620505 | CJ66: -72.538729 | CK66: -74.456952 | CL66: -76.375175 | CM66: -78.293398 | CN66: -80.211622 | CO66: -82.129845 | CP66: -84.048068 | CQ66: -85.966292 | CR66: -87.884515 | CS66: -89.802738 | CT66: -91.720962 | CU66: -93.639185 | CV66: -95.557408 | CW66: -97.475632 | CX66: -99.393855 | CY66: -101.31208 | CZ66: -103.2303 | DA66: -105.14852 | DB66: -107.06675 | DC66: -108.98497 | DD66: -110.90319 | DE66: -112.82142 | DF66: -114.73964 | DG66: -116.65786 | DH66: -118.57609 | DI66: -120.49431 | DJ66: -122.41253 | DK66: -124.33076 | DL66: -126.24898 | DM66: -128.1672 | DN66: -130.08543 | DO66: -132.00462 | DP66: -133.93193 | DQ66: -135.85925
A67: =Customer!$B$10 -> 10.476616 | B67: RBP route, 2029/30 floor | C67: =INDEX($K$62:$DQ$62,$H67)+INDEX($K67:$DQ67,$H67)*(INDEX($K$62:$DQ$62,$H67+1)-INDEX($K$62:$DQ$62,$H67))/(INDEX($K67:$DQ67,$H67)-INDEX($K67:$DQ67,$H67+1)) -> 0.44750364 | D67: =C67/Inputs!$C$82-1 -> -0.49147313 | E67: =(Technical!$B$33*Inputs!$C$19+Technical!$B$32*Inputs!$C$20)/10^6*Costs!$B$8*C67 -> 68.709876 | H67: =MATCH(0,$K67:$DQ67,-1) -> 25 | J67: =A67 -> 10.476616 | K67: 40.597644 | L67: 39.052963 | M67: 37.500829 | N67: 35.948695 | O67: 34.396561 | P67: 32.83188 | Q67: 31.26432 | R67: 29.689812 | S67: 28.072619 | T67: 26.45461 | U67: 24.818384 | V67: 23.178969 | W67: 21.539553 | X67: 19.88827 | Y67: 18.229061 | Z67: 16.569853 | AA67: 14.900306 | AB67: 13.222783 | AC67: 11.545259 | AD67: 9.8562244 | AE67: 8.1595909 | AF67: 6.4589916 | AG67: 4.742025 | AH67: 3.0250583 | AI67: 1.2997765 | AJ67: -0.43241777 | AK67: -2.1686234 | AL67: -3.9149189 | AM67: -5.6633261 | AN67: -7.4226874 | AO67: -9.1841281 | AP67: -10.955603 | AQ67: -12.759445 | AR67: -14.635798 | AS67: -16.512151 | AT67: -18.388505 | AU67: -19.785282 | AV67: -20.819923 | AW67: -22.727991 | AX67: -24.638885 | AY67: -26.549778 | AZ67: -28.460671 | BA67: -30.371564 | BB67: -32.282457 | BC67: -34.193351 | BD67: -36.104244 | BE67: -38.015137 | BF67: -39.92603 | BG67: -41.836923 | BH67: -43.747817 | BI67: -45.65871 | BJ67: -47.569603 | BK67: -49.480496 | BL67: -51.391389 | BM67: -53.302283 | BN67: -55.213176 | BO67: -57.124069 | BP67: -59.034962 | BQ67: -60.945855 | BR67: -62.856749 | BS67: -64.767642 | BT67: -66.678535 | BU67: -68.589428 | BV67: -70.500321 | BW67: -72.411215 | BX67: -74.322108 | BY67: -76.233001 | BZ67: -78.143894 | CA67: -80.054787 | CB67: -81.965681 | CC67: -83.876574 | CD67: -85.787467 | CE67: -87.69836 | CF67: -89.609253 | CG67: -91.520147 | CH67: -93.43104 | CI67: -95.341933 | CJ67: -97.252826 | CK67: -99.163719 | CL67: -101.07461 | CM67: -102.98975 | CN67: -104.90934 | CO67: -106.82919 | CP67: -108.7498 | CQ67: -110.67041 | CR67: -112.59185 | CS67: -114.51353 | CT67: -116.43525 | CU67: -118.35805 | CV67: -120.28085 | CW67: -122.20365 | CX67: -124.12645 | CY67: -126.04976 | CZ67: -127.97373 | DA67: -129.89771 | DB67: -131.82168 | DC67: -133.74681 | DD67: -135.67201 | DE67: -137.59721 | DF67: -139.52364 | DG67: -141.45012 | DH67: -143.37661 | DI67: -145.30398 | DJ67: -147.2318 | DK67: -149.15963 | DL67: -151.08745 | DM67: -153.01528 | DN67: -154.9431 | DO67: -156.87228 | DP67: -158.8015 | DQ67: -160.73072
A68: =Customer!$B$9 -> 6.0982784 | B68: RBP route, 2029/30 cap | C68: =INDEX($K$62:$DQ$62,$H68)+INDEX($K68:$DQ68,$H68)*(INDEX($K$62:$DQ$62,$H68+1)-INDEX($K$62:$DQ$62,$H68))/(INDEX($K68:$DQ68,$H68)-INDEX($K68:$DQ68,$H68+1)) -> 0.33899975 | D68: =C68/Inputs!$C$82-1 -> -0.61477302 | E68: =(Technical!$B$33*Inputs!$C$19+Technical!$B$32*Inputs!$C$20)/10^6*Costs!$B$8*C68 -> 52.050147 | H68: =MATCH(0,$K68:$DQ68,-1) -> 14 | J68: =A68 -> 6.0982784 | K68: 22.961326 | L68: 21.399629 | M68: 19.806777 | N68: 18.193573 | O68: 16.56317 | P68: 14.932768 | Q68: 13.287574 | R68: 11.637235 | S68: 9.9784142 | T68: 8.3096212 | U68: 6.6358915 | V68: 4.9486257 | W68: 3.2521262 | X68: 1.5435679 | Y68: -0.17155594 | Z68: -1.8954684 | AA68: -3.62999 | AB68: -5.3703832 | AC68: -7.121688 | AD68: -8.8815336 | AE68: -10.679324 | AF68: -12.548546 | AG68: -14.417769 | AH68: -15.641233 | AI68: -17.248631 | AJ68: -19.148684 | AK68: -21.050524 | AL68: -22.952364 | AM68: -24.854203 | AN68: -26.756043 | AO68: -28.657883 | AP68: -30.559723 | AQ68: -32.461562 | AR68: -34.363402 | AS68: -36.265242 | AT68: -38.167081 | AU68: -40.068921 | AV68: -41.970761 | AW68: -43.8726 | AX68: -45.77444 | AY68: -47.67628 | AZ68: -49.578119 | BA68: -51.479959 | BB68: -53.381799 | BC68: -55.283638 | BD68: -57.185478 | BE68: -59.087318 | BF68: -60.989157 | BG68: -62.890997 | BH68: -64.792837 | BI68: -66.694677 | BJ68: -68.596516 | BK68: -70.498356 | BL68: -72.400196 | BM68: -74.302035 | BN68: -76.203875 | BO68: -78.112404 | BP68: -80.022593 | BQ68: -81.933666 | BR68: -83.845052 | BS68: -85.757205 | BT68: -87.669644 | BU68: -89.582932 | BV68: -91.496219 | BW68: -93.409507 | BX68: -95.323364 | BY68: -97.237845 | BZ68: -99.152326 | CA68: -101.06793 | CB68: -102.98367 | CC68: -104.90062 | CD68: -106.81767 | CE68: -108.7358 | CF68: -110.65423 | CG68: -112.57266 | CH68: -114.49108 | CI68: -116.41017 | CJ68: -118.33004 | CK68: -120.24992 | CL68: -122.16979 | CM68: -124.08966 | CN68: -126.00953 | CO68: -127.9294 | CP68: -129.84927 | CQ68: -131.76914 | CR68: -133.68901 | CS68: -135.60888 | CT68: -137.52875 | CU68: -139.44862 | CV68: -141.36849 | CW68: -143.28836 | CX68: -145.20823 | CY68: -147.1281 | CZ68: -149.04797 | DA68: -150.96784 | DB68: -152.88771 | DC68: -154.80758 | DD68: -156.72745 | DE68: -158.64732 | DF68: -160.56719 | DG68: -162.48706 | DH68: -164.40694 | DI68: -166.32681 | DJ68: -168.24668 | DK68: -170.16655 | DL68: -172.08642 | DM68: -174.00629 | DN68: -175.92616 | DO68: -177.84603 | DP68: -179.7659 | DQ68: -181.68577

Sheet Customer
A1: CUSTOMER-SIDE BENCHMARKS
A2: Item | B2: Value | C2: Unit | D2: Source
A3: 1. Customer's extra cost through RBP
A4: RBP maximum average procurement cost | B4: =Inputs!$C$85 -> 555 | C4: $/MW-day UCAP
A5: Customer's capacity share per kW of load (FPR 2029/30) | B5: =Inputs!$C$13 -> 0.9232 | C5: MW UCAP per MW
A6: Auction price: 2029/30 cap (base) | B6: =Inputs!$C$32 -> 337.83 | C6: $/MW-day
A7: Auction price: 2029/30 floor | B7: =Inputs!$C$83 -> 181.91 | C7: $/MW-day
A8: Auction price: zero (bound) | B8: 0 | C8: $/MW-day
A9: RBP charge at the 2029/30 cap | B9: =(B4-B6)*B5*365/12/1000 -> 6.0982784 | C9: $/kW-month of load
A10: RBP charge at the 2029/30 floor | B10: =(B4-B7)*B5*365/12/1000 -> 10.476616 | C10: $/kW-month of load
A11: RBP charge if the auction price were zero | B11: =(B4-B8)*B5*365/12/1000 -> 15.58477 | C11: $/kW-month of load
A12: Minimum battery fee | B12: =Results!$B$9 -> 27.653459 | C12: $/kW-month
A13: Fee ÷ RBP charge at zero auction price | B13: =B12/B11 -> 1.7743899 | C13: x
A14: Fee ÷ RBP charge at the 2029/30 cap | B14: =B12/B9 -> 4.5346338 | C14: x
A15: 2. Price per accredited megawatt
A16: Accredited capacity, first year | B16: =Technical!$B$9 -> 45 | C16: MW UCAP
A17: Fee per accredited MW-day | B17: =CashFlow!$D$10*10^6/(B16*365) -> 1010.172 | C17: $/MW-day UCAP
A18: Fee + capacity revenue per accredited MW-day | B18: =CashFlow!$D$12*10^6/(B16*365) -> 1348.002 | C18: $/MW-day UCAP
A19: 3. IRAS credit and dispatch record
A20: IRAS credit rate (non-PAI rate) | B20: =Technical!$B$44*Inputs!$C$63 -> 1592.5558 | C20: $/MWh
A21: Rent per MWh of load | B21: =Results!$B$30*10^6/(Technical!$B$4*8760) -> 142.32343 | C21: $/MWh
A22: Dispatch hours in record (1 Jan 2017 – 21 Sep 2026) | B22: =Technical!$B$21 -> 102.66667 | C22: hours
A23: Dispatch days since 1 Jan 2025 | B23: =COUNTIF(Events!$A$5:$A$20,">="&DATE(2025,1,1)) -> 13 | C23: days
A24: Dispatch hours since 1 Jan 2025 | B24: =SUMPRODUCT((Events!$A$5:$A$20>=DATE(2025,1,1))*Events!$F$5:$F$20) -> 82.166667 | C24: hours
A25: Dispatch hours per year since 1 Jan 2025 | B25: =B24/((DATE(2026,9,21)-DATE(2025,1,1))/365.25) -> 47.788814 | C25: hours/year
A26: 4. On-site gas: capital per accredited kW
A27: Gas peaking capital cost, low | B27: 1100 | C27: $/kW | D27: Lazard LCOE+ (Jul 2026).
A28: Gas peaking capital cost, high | B28: 1650 | C28: $/kW | D28: Lazard LCOE+ (Jul 2026).
A29: Gas combustion turbine rating, dual fuel, 2029/30 | B29: 0.76 | C29: % | D29: PJM ELCC class ratings, 2029/30 BRA.
A30: Gas combustion turbine rating, 2029/30 | B30: 0.59 | C30: % | D30: PJM ELCC class ratings, 2029/30 BRA.
A31: Gas capital per accredited kW, low | B31: =B27/B29 -> 1447.3684 | C31: $/kW UCAP
A32: Gas capital per accredited kW, high | B32: =B28/B30 -> 2796.6102 | C32: $/kW UCAP
A33: Battery capital per accredited kW | B33: =Costs!$B$9*1000/Technical!$B$9 -> 3002.5673 | C33: $/kW UCAP
A34: 5. Scale of the need
A35: Dominion data-center billing demand, 2025 | B35: 4.2 | C35: GW | D35: Dominion data-center forecast (16 Sep 2025).
A36: Dominion data-center billing demand, 2030 | B36: 7 | C36: GW | D36: Dominion data-center forecast (16 Sep 2025).
A37: New capacity that growth needs to leave the IRAS tier | B37: =(B36-B35)*B5 -> 2.58496 | C37: GW UCAP
